Workbook

Sheet LOCALIZACIÓN
B2: PESO RELATIVO
B3: K
B4: FOi | C4: FSi
B5: 0.6 | C5: =1-B5 -> 0.4 | I5: FSi
I6: =+B8 -> San Diego | J6: =SUMPRODUCT(C14:F14,H13:K13) -> 0.32833333
B7: LUGAR | C7: COSTO Ci | D7: 1/Ci | F7: FOi | I7: =+B9 -> Laureles | J7: =SUMPRODUCT(C14:F14,H14:K14) -> 0.24583333 | L7: MPL
B8: San Diego | C8: 1900000 | D8: =1/C8 -> 5.2631579e-07 | F8: =+B8 -> San Diego | G8: =+(D8)/(D11) -> 0.39338459 | I8: =+B10 -> El Guayabo | J8: =SUMPRODUCT(C14:F14,H15:K15) -> 0.42583333 | L8: =+(B5*(G8))+(C5*(J6)) -> 0.36736408
B9: Laureles | C9: 2600000 | D9: =1/C9 -> 3.8461538e-07 | F9: =+B9 -> Laureles | G9: =+(D9)/(D11) -> 0.28747335 | J9: =+SUM(J6:J8) -> 1 | L9: =+(B5*(G9))+(C5*(J7)) -> 0.27081734
B10: El Guayabo | C10: 2342000 | D10: =1/C10 -> 4.2698548e-07 | F10: =+B10 -> El Guayabo | G10: =+(D10)/(D11) -> 0.31914206 | L10: =+(B5*(G10))+(C5*(J8)) -> 0.36181857
C11: Sum 1/Ci | D11: =+SUM(D8:D10) -> 1.3379167e-06 | G11: =+SUM(G8:G10) -> 1 | L11: =+SUM(L8:L10) -> 1
H12: =+C13 -> Seguridad | I12: =+D13 -> Accesibilidad | J12: =+E13 -> Cercania | K12: =+F13 -> Servicios públicos
B13: FACTORES | C13: Seguridad | D13: Accesibilidad | E13: Cercania | F13: Servicios públicos | H13: =+G19 -> 0.4 | I13: =+L19 -> 0.25 | J13: =+G26 -> 0.33333333 | K13: =+L26 -> 0.33333333
B14: Wj | C14: 0.3 | D14: 0.3 | E14: 0.25 | F14: 0.15 | H14: =+G20 -> 0 | I14: =+L20 -> 0.375 | J14: =+G27 -> 0.33333333 | K14: =+L27 -> 0.33333333
B15: Valor de 0 a 1, que la suma de todos de 1 | F15: =+SUM(C14:F14) -> 1 | H15: =+G21 -> 0.6 | I15: =+L21 -> 0.375 | J15: =+G28 -> 0.33333333 | K15: =+L28 -> 0.33333333
B17: FACTORES | C17: =+C13 -> Seguridad | H17: =+D13 -> Accesibilidad
B18: LUGAR | C18: E1 | D18: E2 | E18: E3 | F18: sum | G18: Rij | H18: E1 | I18: E2 | J18: E3 | K18: sum | L18: Rij
B19: =+F8 -> San Diego | C19: 0 | D19: 1 | E19: 1 | F19: =+SUM(C19:E19) -> 2 | G19: =+F19/F22 -> 0.4 | H19: 0 | I19: 1 | J19: 1 | K19: =+SUM(H19:J19) -> 2 | L19: =+K19/K22 -> 0.25
B20: =+F9 -> Laureles | C20: 0 | D20: 0 | E20: 0 | F20: =+SUM(C20:E20) -> 0 | G20: =+F20/F22 -> 0 | H20: 1 | I20: 1 | J20: 1 | K20: =+SUM(H20:J20) -> 3 | L20: =+K20/K22 -> 0.375
B21: =+F10 -> El Guayabo | C21: 1 | D21: 1 | E21: 1 | F21: =+SUM(C21:E21) -> 3 | G21: =+F21/F22 -> 0.6 | H21: 1 | I21: 1 | J21: 1 | K21: =+SUM(H21:J21) -> 3 | L21: =+K21/K22 -> 0.375
D22: Total | F22: =+SUM(F19:F21) -> 5 | G22: =+SUM(G19:G21) -> 1 | I22: Total | K22: =+SUM(K19:K21) -> 8 | L22: =+SUM(L19:L21) -> 1
B24: FACTORES | C24: =+E13 -> Cercania | H24: =+F13 -> Servicios públicos
B25: LUGAR | C25: E1 | D25: E2 | E25: E3 | F25: sum | G25: Rij | H25: E1 | I25: E2 | J25: E3 | K25: sum | L25: Rij
B26: =+F8 -> San Diego | C26: 1 | D26: 1 | E26: 1 | F26: =+SUM(C26:E26) -> 3 | G26: =+F26/F29 -> 0.33333333 | H26: 1 | I26: 1 | J26: 1 | K26: =+SUM(H26:J26) -> 3 | L26: =+K26/K29 -> 0.33333333
B27: =+F9 -> Laureles | C27: 1 | D27: 1 | E27: 1 | F27: =+SUM(C27:E27) -> 3 | G27: =+F27/F29 -> 0.33333333 | H27: 1 | I27: 1 | J27: 1 | K27: =+SUM(H27:J27) -> 3 | L27: =+K27/K29 -> 0.33333333
B28: =+F10 -> El Guayabo | C28: 1 | D28: 1 | E28: 1 | F28: =+SUM(C28:E28) -> 3 | G28: =+F28/F29 -> 0.33333333 | H28: 1 | I28: 1 | J28: 1 | K28: =+SUM(H28:J28) -> 3 | L28: =+K28/K29 -> 0.33333333
D29: Total | F29: =+SUM(F26:F28) -> 9 | G29: =+SUM(G26:G28) -> 1 | I29: Total | K29: =+SUM(K26:K28) -> 9 | L29: =+SUM(L26:L28) -> 1

Sheet PROYECCIONES Y ESTIMACIONES
C2: Capacidad | L2: Estimacion Inflación | P2: Estimacion Aumento Salario
D3: Año 1 | E3: Año 2 | F3: Año 3 | G3: Año 4 | H3: Año 5 | L3: Promedio móvil ponderado | P3: Promedio móvil ponderado
C4: Demanda estimada anual | D4: 390000 | E4: =+ROUNDUP(D4*1.05,0) -> 409500 | F4: =+ROUNDUP(E4*1.05,0) -> 429975 | G4: =+ROUNDUP(F4*1.05,0) -> 451474 | H4: =+ROUNDUP(G4*1.05,0) -> 474048 | L4: Inflacion | N4: Pesos | P4: Inflacion | R4: Pesos
C5: Demanda estimada mensual | D5: =+ROUNDUP(D4/12,0) -> 32500 | E5: =+ROUNDUP(E4/12,0) -> 34125 | F5: =+ROUNDUP(F4/12,0) -> 35832 | G5: =+ROUNDUP(G4/12,0) -> 37623 | H5: =+ROUNDUP(H4/12,0) -> 39504 | L5: 2023 | M5: 0.0928 | N5: 0.2 | P5: 2023 | Q5: 0.16 | R5: 0.2
C6: Promedio pedidos mensuales | D6: =+ROUNDUP(D5*1.4,0) -> 45500 | E6: =+ROUNDUP(E5*1.4,0) -> 47775 | F6: =+ROUNDUP(F5*1.4,0) -> 50165 | G6: =+ROUNDUP(G5*1.4,0) -> 52673 | H6: =+ROUNDUP(H5*1.4,0) -> 55306 | L6: 2024 | M6: 0.052 | N6: 0.3 | P6: 2024 | Q6: 0.121 | R6: 0.3
L7: 2025 | M7: 0.0551 | N7: 0.5 | P7: 2025 | Q7: 0.095 | R7: 0.5
C8: Requerimientos Anuales | D8: Unidades | L8: 2026 | M8: =+SUMPRODUCT(M5:M7,N5:N7) -> 0.06171 | N8: Año 1 | P8: 2026 | Q8: =+SUMPRODUCT(Q5:Q7,R5:R7) -> 0.1158 | R8: Año 1
D9: Año 1 | E9: Año 2 | F9: Año 3 | G9: Año 4 | H9: Año 5 | L9: 2027 | M9: =+SUMPRODUCT(M6:M8,N5:N7) -> 0.057785 | N9: Año 2 | P9: 2027 | Q9: =+SUMPRODUCT(Q6:Q8,R5:R7) -> 0.1106 | R9: Año 2
B10: 1 | C10: Gerente general | D10: 1 | E10: 1 | F10: 1 | G10: 1 | H10: 1 | L10: 2028 | M10: =+SUMPRODUCT(M7:M9,N5:N7) -> 0.0584255 | N10: Año 3 | P10: 2028 | Q10: =+SUMPRODUCT(Q7:Q9,R5:R7) -> 0.10904 | R10: Año 3
B11: 2 | C11: Contador | D11: 1 | E11: =+ROUNDUP(D11*(1+0.05)^1,0) -> 2 | F11: =+ROUNDUP(D11*(1+0.05)^2,0) -> 2 | G11: =+ROUNDUP(D11*(1+0.05)^3,0) -> 2 | H11: =+ROUNDUP(D11*(1+0.05)^4,0) -> 2 | L11: 2029 | M11: =+SUMPRODUCT(M8:M10,N5:N7) -> 0.05889025 | N11: Año 4 | P11: 2029 | Q11: =+SUMPRODUCT(Q8:Q10,R5:R7) -> 0.11086 | R11: Año 4
B12: 3 | C12: Encargado de bodega | D12: 1 | E12: =+ROUNDUP(D12*(1+0.05)^1,0) -> 2 | F12: =+ROUNDUP(D12*(1+0.05)^2,0) -> 2 | G12: =+ROUNDUP(D12*(1+0.05)^3,0) -> 2 | H12: =+ROUNDUP(D12*(1+0.05)^4,0) -> 2 | L12: 2030 | M12: =+SUMPRODUCT(M9:M11,N5:N7) -> 0.058529775 | N12: Año 5 | P12: 2030 | Q12: =+SUMPRODUCT(Q9:Q11,R5:R7) -> 0.110262 | R12: Año 5
B13: 4 | C13: Operario de bodega | D13: 1 | E13: =+ROUNDUP(D13*(1+0.05)^1,0) -> 2 | F13: =+ROUNDUP(D13*(1+0.05)^2,0) -> 2 | G13: =+ROUNDUP(D13*(1+0.05)^3,0) -> 2 | H13: =+ROUNDUP(D13*(1+0.05)^4,0) -> 2
B14: 5 | C14: Encargado de TI | D14: 1 | E14: =+ROUNDUP(D14*(1+0.05)^1,0) -> 2 | F14: =+ROUNDUP(D14*(1+0.05)^2,0) -> 2 | G14: =+ROUNDUP(D14*(1+0.05)^3,0) -> 2 | H14: =+ROUNDUP(D14*(1+0.05)^4,0) -> 2 | L14: Estimacion costo y precio
B15: 6 | C15: Asesor en linea | D15: 2 | E15: =+ROUNDUP(D15*(1+0.05)^1,0) -> 3 | F15: =+ROUNDUP(D15*(1+0.05)^2,0) -> 3 | G15: =+ROUNDUP(D15*(1+0.05)^3,0) -> 3 | H15: =+ROUNDUP(D15*(1+0.05)^4,0) -> 3 | N15: % preferencia | O15: % estimado | R15: Costo
B16: 7 | C16: Aseadora | D16: 1 | E16: =+ROUNDUP(D16*(1+0.05)^1,0) -> 2 | F16: =+ROUNDUP(D16*(1+0.05)^2,0) -> 2 | G16: =+ROUNDUP(D16*(1+0.05)^3,0) -> 2 | H16: =+ROUNDUP(D16*(1+0.05)^4,0) -> 2 | L16: Arabe | M16: 250000 | N16: 0.54 | O16: =+N16+P22 -> 0.65333333 | P16: =+M16*O16 -> 163333.33 | R16: =+(P16+P18+P20)/3 -> 251111.11 | S16: Costo estimado
B17: 8 | C17: Computador | D17: 4 | E17: =+ROUNDUP(D17*(1+0.05)^1,0) -> 5 | F17: =+ROUNDUP(D17*(1+0.05)^2,0) -> 5 | G17: =+ROUNDUP(D17*(1+0.05)^3,0) -> 5 | H17: =+ROUNDUP(D17*(1+0.05)^4,0) -> 5 | R17: =+SUM('CALCULO COSTOS E INVERSIONES'!E38:E47) -> 16450 | S17: Costo de empaque
B18: 9 | C18: Lector de código de barras | D18: 2 | E18: =+ROUNDUP(D18*(1+0.05)^1,0) -> 3 | F18: =+ROUNDUP(D18*(1+0.05)^2,0) -> 3 | G18: =+ROUNDUP(D18*(1+0.05)^3,0) -> 3 | H18: =+ROUNDUP(D18*(1+0.05)^4,0) -> 3 | L18: Diseñador | M18: 500000 | N18: 0.4 | O18: =+N18+P22 -> 0.51333333 | P18: =+M18*O18 -> 256666.67 | R18: =+R16+R17 -> 267561.11 | S18: Costo unitario
B19: 10 | C19: Estanterías metálicas | D19: 5 | E19: =+ROUNDUP(D19*(1+0.05)^1,0) -> 6 | F19: =+ROUNDUP(D19*(1+0.05)^2,0) -> 6 | G19: =+ROUNDUP(D19*(1+0.05)^3,0) -> 6 | H19: =+ROUNDUP(D19*(1+0.05)^4,0) -> 7
B20: 11 | C20: Carro de picking | D20: 1 | E20: =+ROUNDUP(D20*(1+0.05)^1,0) -> 2 | F20: =+ROUNDUP(D20*(1+0.05)^2,0) -> 2 | G20: =+ROUNDUP(D20*(1+0.05)^3,0) -> 2 | H20: =+ROUNDUP(D20*(1+0.05)^4,0) -> 2 | L20: Nicho | M20: 1000000 | N20: 0.22 | O20: =+N20+P22 -> 0.33333333 | P20: =+M20*O20 -> 333333.33 | R20: Precio de venta | S20: 0.3
B21: 12 | C21: Mesa de inspección y pesaje | D21: 2 | E21: =+ROUNDUP(D21*(1+0.05)^1,0) -> 3 | F21: =+ROUNDUP(D21*(1+0.05)^2,0) -> 3 | G21: =+ROUNDUP(D21*(1+0.05)^3,0) -> 3 | H21: =+ROUNDUP(D21*(1+0.05)^4,0) -> 3 | R21: =+ROUNDUP(R18*(1+S20),0) -> 347830
B22: 13 | C22: Mesa de empaque | D22: 2 | E22: =+ROUNDUP(D22*(1+0.05)^1,0) -> 3 | F22: =+ROUNDUP(D22*(1+0.05)^2,0) -> 3 | G22: =+ROUNDUP(D22*(1+0.05)^3,0) -> 3 | H22: =+ROUNDUP(D22*(1+0.05)^4,0) -> 3 | L22: Sin preferencia | O22: 0.34 | P22: =+O22/3 -> 0.11333333
B23: 14 | C23: Báscula digital de precisión | D23: 1 | E23: =+ROUNDUP(D23*(1+0.05)^1,0) -> 2 | F23: =+ROUNDUP(D23*(1+0.05)^2,0) -> 2 | G23: =+ROUNDUP(D23*(1+0.05)^3,0) -> 2 | H23: =+ROUNDUP(D23*(1+0.05)^4,0) -> 2
B24: 15 | C24: Impresora térmica de etiquetas | D24: 1 | E24: =+ROUNDUP(D24*(1+0.05)^1,0) -> 2 | F24: =+ROUNDUP(D24*(1+0.05)^2,0) -> 2 | G24: =+ROUNDUP(D24*(1+0.05)^3,0) -> 2 | H24: =+ROUNDUP(D24*(1+0.05)^4,0) -> 2
B25: 16 | C25: Estación de consolidación | D25: 1 | E25: =+ROUNDUP(D25*(1+0.05)^1,0) -> 2 | F25: =+ROUNDUP(D25*(1+0.05)^2,0) -> 2 | G25: =+ROUNDUP(D25*(1+0.05)^3,0) -> 2 | H25: =+ROUNDUP(D25*(1+0.05)^4,0) -> 2
B26: 17 | C26: Cámaras de seguridad CCTV | D26: 4 | E26: =+ROUNDUP(D26*(1+0.05)^1,0) -> 5 | F26: =+ROUNDUP(D26*(1+0.05)^2,0) -> 5 | G26: =+ROUNDUP(D26*(1+0.05)^3,0) -> 5 | H26: =+ROUNDUP(D26*(1+0.05)^4,0) -> 5
B27: 18 | C27: Sillas ergonómicas | D27: 6 | E27: =+ROUNDUP(D27*(1+0.05)^1,0) -> 7 | F27: =+ROUNDUP(D27*(1+0.05)^2,0) -> 7 | G27: =+ROUNDUP(D27*(1+0.05)^3,0) -> 7 | H27: =+ROUNDUP(D27*(1+0.05)^4,0) -> 8
B28: 19 | C28: Escritorios | D28: 4 | E28: =+ROUNDUP(D28*(1+0.05)^1,0) -> 5 | F28: =+ROUNDUP(D28*(1+0.05)^2,0) -> 5 | G28: =+ROUNDUP(D28*(1+0.05)^3,0) -> 5 | H28: =+ROUNDUP(D28*(1+0.05)^4,0) -> 5
B29: 20 | C29: Cajonera o archivador metálico | D29: 5 | E29: =+ROUNDUP(D29*(1+0.05)^1,0) -> 6 | F29: =+ROUNDUP(D29*(1+0.05)^2,0) -> 6 | G29: =+ROUNDUP(D29*(1+0.05)^3,0) -> 6 | H29: =+ROUNDUP(D29*(1+0.05)^4,0) -> 7
B30: 21 | C30: Impresora Laser | D30: 1 | E30: =+ROUNDUP(D30*(1+0.05)^1,0) -> 2 | F30: =+ROUNDUP(D30*(1+0.05)^2,0) -> 2 | G30: =+ROUNDUP(D30*(1+0.05)^3,0) -> 2 | H30: =+ROUNDUP(D30*(1+0.05)^4,0) -> 2
B31: 22 | C31: Alfombra antiestática | D31: 1 | E31: =+ROUNDUP(D31*(1+0.05)^1,0) -> 2 | F31: =+ROUNDUP(D31*(1+0.05)^2,0) -> 2 | G31: =+ROUNDUP(D31*(1+0.05)^3,0) -> 2 | H31: =+ROUNDUP(D31*(1+0.05)^4,0) -> 2
B32: 23 | C32: Unidad de perfume | D32: =+D4 -> 390000 | E32: =+ROUNDUP(D32*(1+0.05)^1,0) -> 409500 | F32: =+ROUNDUP(D32*(1+0.05)^2,0) -> 429975 | G32: =+ROUNDUP(D32*(1+0.05)^3,0) -> 451474 | H32: =+ROUNDUP(D32*(1+0.05)^4,0) -> 474048
B33: 24 | C33: Caja decorativa individual | D33: =+D4 -> 390000 | E33: =+ROUNDUP(D33*(1+0.05)^1,0) -> 409500 | F33: =+ROUNDUP(D33*(1+0.05)^2,0) -> 429975 | G33: =+ROUNDUP(D33*(1+0.05)^3,0) -> 451474 | H33: =+ROUNDUP(D33*(1+0.05)^4,0) -> 474048
B34: 25 | C34: Papel seda personalizado | D34: =+D33 -> 390000 | E34: =+ROUNDUP(D34*(1+0.05)^1,0) -> 409500 | F34: =+ROUNDUP(D34*(1+0.05)^2,0) -> 429975 | G34: =+ROUNDUP(D34*(1+0.05)^3,0) -> 451474 | H34: =+ROUNDUP(D34*(1+0.05)^4,0) -> 474048
B35: 26 | C35: Cinta decorativa / lazo | D35: =+D34 -> 390000 | E35: =+ROUNDUP(D35*(1+0.05)^1,0) -> 409500 | F35: =+ROUNDUP(D35*(1+0.05)^2,0) -> 429975 | G35: =+ROUNDUP(D35*(1+0.05)^3,0) -> 451474 | H35: =+ROUNDUP(D35*(1+0.05)^4,0) -> 474048
B36: 27 | C36: Bolsa de entrega / envío | D36: =+D35 -> 390000 | E36: =+ROUNDUP(D36*(1+0.05)^1,0) -> 409500 | F36: =+ROUNDUP(D36*(1+0.05)^2,0) -> 429975 | G36: =+ROUNDUP(D36*(1+0.05)^3,0) -> 451474 | H36: =+ROUNDUP(D36*(1+0.05)^4,0) -> 474048
B37: 28 | C37: Etiqueta de envío y código de barras | D37: =+D36 -> 390000 | E37: =+ROUNDUP(D37*(1+0.05)^1,0) -> 409500 | F37: =+ROUNDUP(D37*(1+0.05)^2,0) -> 429975 | G37: =+ROUNDUP(D37*(1+0.05)^3,0) -> 451474 | H37: =+ROUNDUP(D37*(1+0.05)^4,0) -> 474048
B38: 29 | C38: Factura impresa / packing slip | D38: =+D37 -> 390000 | E38: =+ROUNDUP(D38*(1+0.05)^1,0) -> 409500 | F38: =+ROUNDUP(D38*(1+0.05)^2,0) -> 429975 | G38: =+ROUNDUP(D38*(1+0.05)^3,0) -> 451474 | H38: =+ROUNDUP(D38*(1+0.05)^4,0) -> 474048
B39: 30 | C39: Adhesivo de seguridad, autenticidad | D39: =+D4 -> 390000 | E39: =+ROUNDUP(D39*(1+0.05)^1,0) -> 409500 | F39: =+ROUNDUP(D39*(1+0.05)^2,0) -> 429975 | G39: =+ROUNDUP(D39*(1+0.05)^3,0) -> 451474 | H39: =+ROUNDUP(D39*(1+0.05)^4,0) -> 474048
B40: 31 | C40: Cinta adhesiva y material de embalaje | D40: =1000*12 -> 12000 | E40: =+ROUNDUP(D40*(1+0.05)^1,0) -> 12600 | F40: =+ROUNDUP(D40*(1+0.05)^2,0) -> 13230 | G40: =+ROUNDUP(D40*(1+0.05)^3,0) -> 13892 | H40: =+ROUNDUP(D40*(1+0.05)^4,0) -> 14587
B41: 32 | C41: Guantes y elementos de protección | D41: =500*12 -> 6000 | E41: =+ROUNDUP(D41*(1+0.05)^1,0) -> 6300 | F41: =+ROUNDUP(D41*(1+0.05)^2,0) -> 6615 | G41: =+ROUNDUP(D41*(1+0.05)^3,0) -> 6946 | H41: =+ROUNDUP(D41*(1+0.05)^4,0) -> 7294
B42: 33 | C42: Numero de pedidos | D42: =+D4 -> 390000 | E42: =+ROUNDUP(D42*(1+0.05)^1,0) -> 409500 | F42: =+ROUNDUP(D42*(1+0.05)^2,0) -> 429975 | G42: =+ROUNDUP(D42*(1+0.05)^3,0) -> 451474 | H42: =+ROUNDUP(D42*(1+0.05)^4,0) -> 474048

Sheet CALCULO COSTOS E INVERSIONES
G2: Inflacion
G3: =+'PROYECCIONES Y ESTIMACIONES'!M8 -> 0.06171 | J3: =+'PROYECCIONES Y ESTIMACIONES'!M9 -> 0.057785 | M3: =+'PROYECCIONES Y ESTIMACIONES'!M10 -> 0.0584255 | P3: =+'PROYECCIONES Y ESTIMACIONES'!M11 -> 0.05889025 | S3: =+'PROYECCIONES Y ESTIMACIONES'!M12 -> 0.058529775
B5: Inversion inicial
E7: Año 0 | H7: Año 1 | K7: Año 2 | N7: Año 3 | Q7: Año 4 | T7: Año 5
C8: Equipo | D8: Vida util/periodo | E8: Cant | F8: Valor unitario | G8: Valor total | H8: Cant | I8: Valor unitario | J8: Valor total | K8: Cant | L8: Valor unitario | M8: Valor total | N8: Cant | O8: Valor unitario | P8: Valor total | Q8: Cant | R8: Valor unitario | S8: Valor total | T8: Cant | U8: Valor unitario | V8: Valor total
B9: 1 | C9: Computador | D9: 5 | E9: 4 | F9: 2500000 | G9: =+F9*E9 -> 10000000 | H9: =+'PROYECCIONES Y ESTIMACIONES'!D17-E9 -> 0 | I9: =+F9*(1+G$3) -> 2654275 | J9: =+I9*H9 -> 0 | K9: =+'PROYECCIONES Y ESTIMACIONES'!E17-E9 -> 1 | L9: =+I9*(1+J$3) -> 2807652.3 | M9: =+L9*K9 -> 2807652.3 | N9: =+'PROYECCIONES Y ESTIMACIONES'!F17-(E9+K9) -> 0 | O9: =+L9*(1+M$3) -> 2971690.8 | P9: =+O9*N9 -> 0 | Q9: =+'PROYECCIONES Y ESTIMACIONES'!G17-(E9+K9+N9) -> 0 | R9: =+O9*(1+P$3) -> 3146694.4 | S9: =+R9*Q9 -> 0 | T9: =+'PROYECCIONES Y ESTIMACIONES'!H17-(E9+K9+N9+Q9) -> 0 | U9: =+R9*(1+S$3) -> 3330869.7 | V9: =+U9*T9 -> 0
B10: 2 | C10: Lector de código de barras | D10: 5 | E10: 2 | F10: 460000 | G10: =+F10*E10 -> 920000 | H10: =+'PROYECCIONES Y ESTIMACIONES'!D18-E10 -> 0 | I10: =+F10*(1+G$3) -> 488386.6 | J10: =+I10*H10 -> 0 | K10: =+'PROYECCIONES Y ESTIMACIONES'!E18-E10 -> 1 | L10: =+I10*(1+J$3) -> 516608.02 | M10: =+L10*K10 -> 516608.02 | N10: =+'PROYECCIONES Y ESTIMACIONES'!F18-(E10+K10) -> 0 | O10: =+L10*(1+M$3) -> 546791.1 | P10: =+O10*N10 -> 0 | Q10: =+'PROYECCIONES Y ESTIMACIONES'!G18-(E10+K10+N10) -> 0 | R10: =+O10*(1+P$3) -> 578991.77 | S10: =+R10*Q10 -> 0 | T10: =+'PROYECCIONES Y ESTIMACIONES'!H18-(E10+K10+N10+Q10) -> 0 | U10: =+R10*(1+S$3) -> 612880.02 | V10: =+U10*T10 -> 0
B11: 3 | C11: Estanterías metálicas | D11: 10 | E11: 5 | F11: 1000000 | G11: =+F11*E11 -> 5000000 | H11: =+'PROYECCIONES Y ESTIMACIONES'!D19-E11 -> 0 | I11: =+F11*(1+G$3) -> 1061710 | J11: =+I11*H11 -> 0 | K11: =+'PROYECCIONES Y ESTIMACIONES'!E19-E11 -> 1 | L11: =+I11*(1+J$3) -> 1123060.9 | M11: =+L11*K11 -> 1123060.9 | N11: =+'PROYECCIONES Y ESTIMACIONES'!F19-(E11+K11) -> 0 | O11: =+L11*(1+M$3) -> 1188676.3 | P11: =+O11*N11 -> 0 | Q11: =+'PROYECCIONES Y ESTIMACIONES'!G19-(E11+K11+N11) -> 0 | R11: =+O11*(1+P$3) -> 1258677.8 | S11: =+R11*Q11 -> 0 | T11: =+'PROYECCIONES Y ESTIMACIONES'!H19-(E11+K11+N11+Q11) -> 1 | U11: =+R11*(1+S$3) -> 1332347.9 | V11: =+U11*T11 -> 1332347.9
B12: 4 | C12: Carro de picking | D12: 5 | E12: 1 | F12: 655000 | G12: =+F12*E12 -> 655000 | H12: =+'PROYECCIONES Y ESTIMACIONES'!D20-E12 -> 0 | I12: =+F12*(1+G$3) -> 695420.05 | J12: =+I12*H12 -> 0 | K12: =+'PROYECCIONES Y ESTIMACIONES'!E20-E12 -> 1 | L12: =+I12*(1+J$3) -> 735604.9 | M12: =+L12*K12 -> 735604.9 | N12: =+'PROYECCIONES Y ESTIMACIONES'!F20-(E12+K12) -> 0 | O12: =+L12*(1+M$3) -> 778582.98 | P12: =+O12*N12 -> 0 | Q12: =+'PROYECCIONES Y ESTIMACIONES'!G20-(E12+K12+N12) -> 0 | R12: =+O12*(1+P$3) -> 824433.93 | S12: =+R12*Q12 -> 0 | T12: =+'PROYECCIONES Y ESTIMACIONES'!H20-(E12+K12+N12+Q12) -> 0 | U12: =+R12*(1+S$3) -> 872687.86 | V12: =+U12*T12 -> 0
B13: 5 | C13: Mesa de inspección y pesaje | D13: 10 | E13: 2 | F13: 500000 | G13: =+F13*E13 -> 1000000 | H13: =+'PROYECCIONES Y ESTIMACIONES'!D21-E13 -> 0 | I13: =+F13*(1+G$3) -> 530855 | J13: =+I13*H13 -> 0 | K13: =+'PROYECCIONES Y ESTIMACIONES'!E21-E13 -> 1 | L13: =+I13*(1+J$3) -> 561530.46 | M13: =+L13*K13 -> 561530.46 | N13: =+'PROYECCIONES Y ESTIMACIONES'!F21-(E13+K13) -> 0 | O13: =+L13*(1+M$3) -> 594338.15 | P13: =+O13*N13 -> 0 | Q13: =+'PROYECCIONES Y ESTIMACIONES'!G21-(E13+K13+N13) -> 0 | R13: =+O13*(1+P$3) -> 629338.88 | S13: =+R13*Q13 -> 0 | T13: =+'PROYECCIONES Y ESTIMACIONES'!H21-(E13+K13+N13+Q13) -> 0 | U13: =+R13*(1+S$3) -> 666173.94 | V13: =+U13*T13 -> 0
B14: 6 | C14: Mesa de empaque con superficie lisa y selladora | D14: 5 | E14: 2 | F14: 350000 | G14: =+F14*E14 -> 700000 | H14: =+'PROYECCIONES Y ESTIMACIONES'!D22-E14 -> 0 | I14: =+F14*(1+G$3) -> 371598.5 | J14: =+I14*H14 -> 0 | K14: =+'PROYECCIONES Y ESTIMACIONES'!E22-E14 -> 1 | L14: =+I14*(1+J$3) -> 393071.32 | M14: =+L14*K14 -> 393071.32 | N14: =+'PROYECCIONES Y ESTIMACIONES'!F22-(E14+K14) -> 0 | O14: =+L14*(1+M$3) -> 416036.71 | P14: =+O14*N14 -> 0 | Q14: =+'PROYECCIONES Y ESTIMACIONES'!G22-(E14+K14+N14) -> 0 | R14: =+O14*(1+P$3) -> 440537.21 | S14: =+R14*Q14 -> 0 | T14: =+'PROYECCIONES Y ESTIMACIONES'!H22-(E14+K14+N14+Q14) -> 0 | U14: =+R14*(1+S$3) -> 466321.76 | V14: =+U14*T14 -> 0
B15: 7 | C15: Báscula digital de precisión | D15: 5 | E15: 1 | F15: 200000 | G15: =+F15*E15 -> 200000 | H15: =+'PROYECCIONES Y ESTIMACIONES'!D23-E15 -> 0 | I15: =+F15*(1+G$3) -> 212342 | J15: =+I15*H15 -> 0 | K15: =+'PROYECCIONES Y ESTIMACIONES'!E23-E15 -> 1 | L15: =+I15*(1+J$3) -> 224612.18 | M15: =+L15*K15 -> 224612.18 | N15: =+'PROYECCIONES Y ESTIMACIONES'!F23-(E15+K15) -> 0 | O15: =+L15*(1+M$3) -> 237735.26 | P15: =+O15*N15 -> 0 | Q15: =+'PROYECCIONES Y ESTIMACIONES'!G23-(E15+K15+N15) -> 0 | R15: =+O15*(1+P$3) -> 251735.55 | S15: =+R15*Q15 -> 0 | T15: =+'PROYECCIONES Y ESTIMACIONES'!H23-(E15+K15+N15+Q15) -> 0 | U15: =+R15*(1+S$3) -> 266469.58 | V15: =+U15*T15 -> 0
B16: 8 | C16: Impresora térmica de etiquetas | D16: 5 | E16: 1 | F16: 610000 | G16: =+F16*E16 -> 610000 | H16: =+'PROYECCIONES Y ESTIMACIONES'!D24-E16 -> 0 | I16: =+F16*(1+G$3) -> 647643.1 | J16: =+I16*H16 -> 0 | K16: =+'PROYECCIONES Y ESTIMACIONES'!E24-E16 -> 1 | L16: =+I16*(1+J$3) -> 685067.16 | M16: =+L16*K16 -> 685067.16 | N16: =+'PROYECCIONES Y ESTIMACIONES'!F24-(E16+K16) -> 0 | O16: =+L16*(1+M$3) -> 725092.55 | P16: =+O16*N16 -> 0 | Q16: =+'PROYECCIONES Y ESTIMACIONES'!G24-(E16+K16+N16) -> 0 | R16: =+O16*(1+P$3) -> 767793.43 | S16: =+R16*Q16 -> 0 | T16: =+'PROYECCIONES Y ESTIMACIONES'!H24-(E16+K16+N16+Q16) -> 0 | U16: =+R16*(1+S$3) -> 812732.21 | V16: =+U16*T16 -> 0
B17: 9 | C17: Estación de consolidación (mesa + rack + zona carga) | D17: 10 | E17: 1 | F17: 1000000 | G17: =+F17*E17 -> 1000000 | H17: =+'PROYECCIONES Y ESTIMACIONES'!D25-E17 -> 0 | I17: =+F17*(1+G$3) -> 1061710 | J17: =+I17*H17 -> 0 | K17: =+'PROYECCIONES Y ESTIMACIONES'!E25-E17 -> 1 | L17: =+I17*(1+J$3) -> 1123060.9 | M17: =+L17*K17 -> 1123060.9 | N17: =+'PROYECCIONES Y ESTIMACIONES'!F25-(E17+K17) -> 0 | O17: =+L17*(1+M$3) -> 1188676.3 | P17: =+O17*N17 -> 0 | Q17: =+'PROYECCIONES Y ESTIMACIONES'!G25-(E17+K17+N17) -> 0 | R17: =+O17*(1+P$3) -> 1258677.8 | S17: =+R17*Q17 -> 0 | T17: =+'PROYECCIONES Y ESTIMACIONES'!H25-(E17+K17+N17+Q17) -> 0 | U17: =+R17*(1+S$3) -> 1332347.9 | V17: =+U17*T17 -> 0
B18: 10 | C18: Cámaras de seguridad CCTV | D18: 5 | E18: 4 | F18: 250000 | G18: =+F18*E18 -> 1000000 | H18: =+'PROYECCIONES Y ESTIMACIONES'!D26-E18 -> 0 | I18: =+F18*(1+G$3) -> 265427.5 | J18: =+I18*H18 -> 0 | K18: =+'PROYECCIONES Y ESTIMACIONES'!E26-E18 -> 1 | L18: =+I18*(1+J$3) -> 280765.23 | M18: =+L18*K18 -> 280765.23 | N18: =+'PROYECCIONES Y ESTIMACIONES'!F26-(E18+K18) -> 0 | O18: =+L18*(1+M$3) -> 297169.08 | P18: =+O18*N18 -> 0 | Q18: =+'PROYECCIONES Y ESTIMACIONES'!G26-(E18+K18+N18) -> 0 | R18: =+O18*(1+P$3) -> 314669.44 | S18: =+R18*Q18 -> 0 | T18: =+'PROYECCIONES Y ESTIMACIONES'!H26-(E18+K18+N18+Q18) -> 0 | U18: =+R18*(1+S$3) -> 333086.97 | V18: =+U18*T18 -> 0
B19: 11 | C19: Sillas ergonómicas | D19: 5 | E19: 6 | F19: 350000 | G19: =+F19*E19 -> 2100000 | H19: =+'PROYECCIONES Y ESTIMACIONES'!D27-E19 -> 0 | I19: =+F19*(1+G$3) -> 371598.5 | J19: =+I19*H19 -> 0 | K19: =+'PROYECCIONES Y ESTIMACIONES'!E27-E19 -> 1 | L19: =+I19*(1+J$3) -> 393071.32 | M19: =+L19*K19 -> 393071.32 | N19: =+'PROYECCIONES Y ESTIMACIONES'!F27-(E19+K19) -> 0 | O19: =+L19*(1+M$3) -> 416036.71 | P19: =+O19*N19 -> 0 | Q19: =+'PROYECCIONES Y ESTIMACIONES'!G27-(E19+K19+N19) -> 0 | R19: =+O19*(1+P$3) -> 440537.21 | S19: =+R19*Q19 -> 0 | T19: =+'PROYECCIONES Y ESTIMACIONES'!H27-(E19+K19+N19+Q19) -> 1 | U19: =+R19*(1+S$3) -> 466321.76 | V19: =+U19*T19 -> 466321.76
B20: 12 | C20: Escritorios | D20: 10 | E20: 4 | F20: 500000 | G20: =+F20*E20 -> 2000000 | H20: =+'PROYECCIONES Y ESTIMACIONES'!D28-E20 -> 0 | I20: =+F20*(1+G$3) -> 530855 | J20: =+I20*H20 -> 0 | K20: =+'PROYECCIONES Y ESTIMACIONES'!E28-E20 -> 1 | L20: =+I20*(1+J$3) -> 561530.46 | M20: =+L20*K20 -> 561530.46 | N20: =+'PROYECCIONES Y ESTIMACIONES'!F28-(E20+K20) -> 0 | O20: =+L20*(1+M$3) -> 594338.15 | P20: =+O20*N20 -> 0 | Q20: =+'PROYECCIONES Y ESTIMACIONES'!G28-(E20+K20+N20) -> 0 | R20: =+O20*(1+P$3) -> 629338.88 | S20: =+R20*Q20 -> 0 | T20: =+'PROYECCIONES Y ESTIMACIONES'!H28-(E20+K20+N20+Q20) -> 0 | U20: =+R20*(1+S$3) -> 666173.94 | V20: =+U20*T20 -> 0
... B23: 15 | C23: Alfombra antiestática | D23: 5 | E23: 1 | F23: 70000 | G23: =+F23*E23 -> 70000 | H23: =+'PROYECCIONES Y ESTIMACIONES'!D31-E23 -> 0 | I23: =+F23*(1+G$3) -> 74319.7 | J23: =+I23*H23 -> 0 | K23: =+'PROYECCIONES Y ESTIMACIONES'!E31-E23 -> 1 | L23: =+I23*(1+J$3) -> 78614.264 | M23: =+L23*K23 -> 78614.264 | N23: =+'PROYECCIONES Y ESTIMACIONES'!F31-(E23+K23) -> 0 | O23: =+L23*(1+M$3) -> 83207.342 | P23: =+O23*N23 -> 0 | Q23: =+'PROYECCIONES Y ESTIMACIONES'!G31-(E23+K23+N23) -> 0 | R23: =+O23*(1+P$3) -> 88107.443 | S23: =+R23*Q23 -> 0 | T23: =+'PROYECCIONES Y ESTIMACIONES'!H31-(E23+K23+N23+Q23) -> 0 | U23: =+R23*(1+S$3) -> 93264.351 | V23: =+U23*T23 -> 0
B24: 16 | C24: UPS o sistema de respaldo eléctrico (unico pago) | D24: 5 | E24: 1 | F24: 1700000 | G24: =+F24*E24 -> 1700000
B25: 17 | C25: Instalacion (Montaje de red y adecuación eléctrica ) | D25: 5 | E25: 1 | F25: 800000 | G25: =+F25*E25 -> 800000
B26: 18 | C26: Adecuacion del local | D26: 5 | E26: 1 | F26: 2700000 | G26: =+F26*E26 -> 2700000 | J26: Activos fijos depreciables
B27: 19 | C27: Desarrollo web y app e-commerce | D27: 5 | E27: 1 | F27: 7500000 | G27: =+F27*E27 -> 7500000 | J27: Activos diferidos
B28: 20 | C28: Integración con pasarelas de pago y logística | D28: 5 | E28: 1 | F28: 4000000 | G28: =+F28*E28 -> 4000000
B29: 21 | C29: Publicidad digital inicial | E29: 1 | F29: =12000000+8000000+5000000 -> 25000000 | G29: =+F29*E29 -> 25000000
F30: , | W30: Total
E31: Total inversion | G31: =SUM(G9:G30) -> 70705000 | H31: Total inversion | J31: =SUM(J9:J23) -> 0 | K31: Total inversion | M31: =SUM(M9:M23) -> 11674218 | N31: Total inversion | P31: =SUM(P9:P23) -> 0 | Q31: Total inversion | S31: =SUM(S9:S23) -> 0 | T31: Total inversion | V31: =SUM(V9:V23) -> 2398226.2 | W31: =+SUM(G31+J31+M31+P31+S31+V31) -> 84777444
B33: Costos variables
D35: Año 0 | G35: Año 1 | J35: Año 2 | M35: Año 3 | P35: Año 4 | S35: Año 5
C36: Insumo o material | D36: Cant | E36: Costo unitario | F36: Costo total | G36: Cant | H36: Costo unitario | I36: Costo total | J36: Cant | K36: Costo unitario | L36: Costo total | M36: Cant | N36: Costo unitario | O36: Costo total | P36: Cant | Q36: Costo unitario | R36: Costo total | S36: Cant | T36: Costo unitario | U36: Costo total
B37: 1 | C37: Unidad de perfume | D37: =+'PROYECCIONES Y ESTIMACIONES'!D32 -> 390000 | E37: =+'PROYECCIONES Y ESTIMACIONES'!R18 -> 267561.11 | F37: =+D37*E37 -> 1.0434883e+11 | G37: =+D37 -> 390000 | H37: =+E37*(1+G$3) -> 284072.31 | I37: =+G37*H37 -> 1.107882e+11 | J37: =+'PROYECCIONES Y ESTIMACIONES'!E32 -> 409500 | K37: =+H37*(1+J$3) -> 300487.43 | L37: =+J37*K37 -> 1.230496e+11 | M37: =+'PROYECCIONES Y ESTIMACIONES'!F32 -> 429975 | N37: =+K37*(1+M$3) -> 318043.55 | O37: =+M37*N37 -> 1.3675078e+11 | P37: =+'PROYECCIONES Y ESTIMACIONES'!G32 -> 451474 | Q37: =+N37*(1+P$3) -> 336773.22 | R37: =+P37*Q37 -> 1.5204435e+11 | S37: =+'PROYECCIONES Y ESTIMACIONES'!H32 -> 474048 | T37: =+Q37*(1+S$3) -> 356484.48 | U37: =+S37*T37 -> 1.6899075e+11
B38: 2 | C38: Caja decorativa individual | D38: =+'PROYECCIONES Y ESTIMACIONES'!D33 -> 390000 | E38: 1800 | F38: =+D38*E38 -> 702000000 | G38: =+D38 -> 390000 | H38: =+E38*(1+G$3) -> 1911.078 | I38: =+G38*H38 -> 745320420 | J38: =+'PROYECCIONES Y ESTIMACIONES'!E33 -> 409500 | K38: =+H38*(1+J$3) -> 2021.5096 | L38: =+J38*K38 -> 8.278082e+08 | M38: =+'PROYECCIONES Y ESTIMACIONES'!F33 -> 429975 | N38: =+K38*(1+M$3) -> 2139.6174 | O38: =+M38*N38 -> 9.1998197e+08 | P38: =+'PROYECCIONES Y ESTIMACIONES'!G33 -> 451474 | Q38: =+N38*(1+P$3) -> 2265.62 | R38: =+P38*Q38 -> 1.0228685e+09 | S38: =+'PROYECCIONES Y ESTIMACIONES'!H33 -> 474048 | T38: =+Q38*(1+S$3) -> 2398.2262 | U38: =+S38*T38 -> 1.1368743e+09
B39: 3 | C39: Papel seda personalizado | D39: =+'PROYECCIONES Y ESTIMACIONES'!D34 -> 390000 | E39: 200 | F39: =+D39*E39 -> 78000000 | G39: =+D39 -> 390000 | H39: =+E39*(1+G$3) -> 212.342 | I39: =+G39*H39 -> 82813380 | J39: =+'PROYECCIONES Y ESTIMACIONES'!E34 -> 409500 | K39: =+H39*(1+J$3) -> 224.61218 | L39: =+J39*K39 -> 91978689 | M39: =+'PROYECCIONES Y ESTIMACIONES'!F34 -> 429975 | N39: =+K39*(1+M$3) -> 237.73526 | O39: =+M39*N39 -> 1.0222022e+08 | P39: =+'PROYECCIONES Y ESTIMACIONES'!G34 -> 451474 | Q39: =+N39*(1+P$3) -> 251.73555 | R39: =+P39*Q39 -> 1.1365206e+08 | S39: =+'PROYECCIONES Y ESTIMACIONES'!H34 -> 474048 | T39: =+Q39*(1+S$3) -> 266.46958 | U39: =+S39*T39 -> 1.2631937e+08
B40: 4 | C40: Cinta decorativa / lazo | D40: =+'PROYECCIONES Y ESTIMACIONES'!D35 -> 390000 | E40: 150 | F40: =+D40*E40 -> 58500000 | G40: =+D40 -> 390000 | H40: =+E40*(1+G$3) -> 159.2565 | I40: =+G40*H40 -> 62110035 | J40: =+'PROYECCIONES Y ESTIMACIONES'!E35 -> 409500 | K40: =+H40*(1+J$3) -> 168.45914 | L40: =+J40*K40 -> 68984017 | M40: =+'PROYECCIONES Y ESTIMACIONES'!F35 -> 429975 | N40: =+K40*(1+M$3) -> 178.30145 | O40: =+M40*N40 -> 76665164 | P40: =+'PROYECCIONES Y ESTIMACIONES'!G35 -> 451474 | Q40: =+N40*(1+P$3) -> 188.80166 | R40: =+P40*Q40 -> 85239042 | S40: =+'PROYECCIONES Y ESTIMACIONES'!H35 -> 474048 | T40: =+Q40*(1+S$3) -> 199.85218 | U40: =+S40*T40 -> 94739527
B41: 5 | C41: Bolsa de entrega / envío | D41: =+'PROYECCIONES Y ESTIMACIONES'!D36 -> 390000 | E41: 500 | F41: =+D41*E41 -> 195000000 | G41: =+D41 -> 390000 | H41: =+E41*(1+G$3) -> 530.855 | I41: =+G41*H41 -> 207033450 | J41: =+'PROYECCIONES Y ESTIMACIONES'!E36 -> 409500 | K41: =+H41*(1+J$3) -> 561.53046 | L41: =+J41*K41 -> 2.2994672e+08 | M41: =+'PROYECCIONES Y ESTIMACIONES'!F36 -> 429975 | N41: =+K41*(1+M$3) -> 594.33815 | O41: =+M41*N41 -> 2.5555055e+08 | P41: =+'PROYECCIONES Y ESTIMACIONES'!G36 -> 451474 | Q41: =+N41*(1+P$3) -> 629.33888 | R41: =+P41*Q41 -> 2.8413014e+08 | S41: =+'PROYECCIONES Y ESTIMACIONES'!H36 -> 474048 | T41: =+Q41*(1+S$3) -> 666.17394 | U41: =+S41*T41 -> 3.1579842e+08
B42: 6 | C42: Etiqueta de envío y código de barras | D42: =+'PROYECCIONES Y ESTIMACIONES'!D37 -> 390000 | E42: 100 | F42: =+D42*E42 -> 39000000 | G42: =+D42 -> 390000 | H42: =+E42*(1+G$3) -> 106.171 | I42: =+G42*H42 -> 41406690 | J42: =+'PROYECCIONES Y ESTIMACIONES'!E37 -> 409500 | K42: =+H42*(1+J$3) -> 112.30609 | L42: =+J42*K42 -> 45989344 | M42: =+'PROYECCIONES Y ESTIMACIONES'!F37 -> 429975 | N42: =+K42*(1+M$3) -> 118.86763 | O42: =+M42*N42 -> 51110110 | P42: =+'PROYECCIONES Y ESTIMACIONES'!G37 -> 451474 | Q42: =+N42*(1+P$3) -> 125.86778 | R42: =+P42*Q42 -> 56826028 | S42: =+'PROYECCIONES Y ESTIMACIONES'!H37 -> 474048 | T42: =+Q42*(1+S$3) -> 133.23479 | U42: =+S42*T42 -> 63159685
B43: 7 | C43: Factura impresa / packing slip | D43: =+'PROYECCIONES Y ESTIMACIONES'!D38 -> 390000 | E43: 80 | F43: =+D43*E43 -> 31200000 | G43: =+D43 -> 390000 | H43: =+E43*(1+G$3) -> 84.9368 | I43: =+G43*H43 -> 33125352 | J43: =+'PROYECCIONES Y ESTIMACIONES'!E38 -> 409500 | K43: =+H43*(1+J$3) -> 89.844873 | L43: =+J43*K43 -> 36791475 | M43: =+'PROYECCIONES Y ESTIMACIONES'!F38 -> 429975 | N43: =+K43*(1+M$3) -> 95.094105 | O43: =+M43*N43 -> 40888088 | P43: =+'PROYECCIONES Y ESTIMACIONES'!G38 -> 451474 | Q43: =+N43*(1+P$3) -> 100.69422 | R43: =+P43*Q43 -> 45460822 | S43: =+'PROYECCIONES Y ESTIMACIONES'!H38 -> 474048 | T43: =+Q43*(1+S$3) -> 106.58783 | U43: =+S43*T43 -> 50527748
B44: 8 | C44: Adhesivo de seguridad / sello autenticidad | D44: =+'PROYECCIONES Y ESTIMACIONES'!D39 -> 390000 | E44: 120 | F44: =+D44*E44 -> 46800000 | G44: =+D44 -> 390000 | H44: =+E44*(1+G$3) -> 127.4052 | I44: =+G44*H44 -> 49688028 | J44: =+'PROYECCIONES Y ESTIMACIONES'!E39 -> 409500 | K44: =+H44*(1+J$3) -> 134.76731 | L44: =+J44*K44 -> 55187213 | M44: =+'PROYECCIONES Y ESTIMACIONES'!F39 -> 429975 | N44: =+K44*(1+M$3) -> 142.64116 | O44: =+M44*N44 -> 61332131 | P44: =+'PROYECCIONES Y ESTIMACIONES'!G39 -> 451474 | Q44: =+N44*(1+P$3) -> 151.04133 | R44: =+P44*Q44 -> 68191234 | S44: =+'PROYECCIONES Y ESTIMACIONES'!H39 -> 474048 | T44: =+Q44*(1+S$3) -> 159.88175 | U44: =+S44*T44 -> 75791622
B45: 9 | C45: Cinta adhesiva y material de embalaje | D45: =+'PROYECCIONES Y ESTIMACIONES'!D40 -> 12000 | E45: 2000 | F45: =+D45*E45 -> 24000000 | G45: =+D45 -> 12000 | H45: =+E45*(1+G$3) -> 2123.42 | I45: =+G45*H45 -> 25481040 | J45: =+'PROYECCIONES Y ESTIMACIONES'!E40 -> 12600 | K45: =+H45*(1+J$3) -> 2246.1218 | L45: =+J45*K45 -> 28301135 | M45: =+'PROYECCIONES Y ESTIMACIONES'!F40 -> 13230 | N45: =+K45*(1+M$3) -> 2377.3526 | O45: =+M45*N45 -> 31452375 | P45: =+'PROYECCIONES Y ESTIMACIONES'!G40 -> 13892 | Q45: =+N45*(1+P$3) -> 2517.3555 | R45: =+P45*Q45 -> 34971103 | S45: =+'PROYECCIONES Y ESTIMACIONES'!H40 -> 14587 | T45: =+Q45*(1+S$3) -> 2664.6958 | U45: =+S45*T45 -> 38869917
B46: 10 | C46: Guantes y elementos de protección | D46: =+'PROYECCIONES Y ESTIMACIONES'!D41 -> 6000 | E46: 1500 | F46: =+D46*E46 -> 9000000 | G46: =+D46 -> 6000 | H46: =+E46*(1+G$3) -> 1592.565 | I46: =+G46*H46 -> 9555390 | J46: =+'PROYECCIONES Y ESTIMACIONES'!E41 -> 6300 | K46: =+H46*(1+J$3) -> 1684.5914 | L46: =+J46*K46 -> 10612926 | M46: =+'PROYECCIONES Y ESTIMACIONES'!F41 -> 6615 | N46: =+K46*(1+M$3) -> 1783.0145 | O46: =+M46*N46 -> 11794641 | P46: =+'PROYECCIONES Y ESTIMACIONES'!G41 -> 6946 | Q46: =+N46*(1+P$3) -> 1888.0166 | R46: =+P46*Q46 -> 13114164 | S46: =+'PROYECCIONES Y ESTIMACIONES'!H41 -> 7294 | T46: =+Q46*(1+S$3) -> 1998.5218 | U46: =+S46*T46 -> 14577218
B47: 11 | C47: Costo de envio de pedido | D47: =+'PROYECCIONES Y ESTIMACIONES'!D42 -> 390000 | E47: 10000 | F47: =+D47*E47 -> 3900000000 | G47: =+D47 -> 390000 | H47: =+E47*(1+G$3) -> 10617.1 | I47: =+G47*H47 -> 4.140669e+09 | J47: =+'PROYECCIONES Y ESTIMACIONES'!E42 -> 409500 | K47: =+H47*(1+J$3) -> 11230.609 | L47: =+J47*K47 -> 4.5989344e+09 | M47: =+'PROYECCIONES Y ESTIMACIONES'!F42 -> 429975 | N47: =+K47*(1+M$3) -> 11886.763 | O47: =+M47*N47 -> 5.111011e+09 | P47: =+'PROYECCIONES Y ESTIMACIONES'!G42 -> 451474 | Q47: =+N47*(1+P$3) -> 12586.778 | R47: =+P47*Q47 -> 5.6826028e+09 | S47: =+'PROYECCIONES Y ESTIMACIONES'!H42 -> 474048 | T47: =+Q47*(1+S$3) -> 13323.479 | U47: =+S47*T47 -> 6.3159685e+09
K48: =+H48*(1+J$3) -> 0 | N48: =+K48*(1+M$3) -> 0 | Q48: =+N48*(1+P$3) -> 0 | T48: =+Q48*(1+S$3) -> 0
F49: =+SUM(F37:F47) -> 1.0943233e+11 | G49: Total Costos variables | I49: =SUM(I37:I47) -> 1.161854e+11 | J49: Total Costos variables | L49: =SUM(L37:L47) -> 1.2904413e+11 | M49: Total Costos variables | O49: =SUM(O37:O47) -> 1.4341278e+11 | P49: Total Costos variables | R49: =SUM(R37:R47) -> 1.5945141e+11 | S49: Total Costos variables | U49: =SUM(U37:U47) -> 1.7722338e+11 | V49: =+SUM(I49+L49+O49+R49+U49) -> 7.2531711e+11
B52: Costos fijos
E54: Año 0 | G54: Año 1 | J54: Año 2 | M54: Año 3 | P54: Año 4 | S54: Año 5
B55: 1 | C55: Software y licencias | D55: mes | E55: 3000000 | F55: =+E55*12 -> 36000000 | G55: =+F55*(1+G$3) -> 38221560 | J55: =+G55*(1+J$3) -> 40430193 | M55: =+J55*(1+M$3)^1 -> 42792347 | P55: =+M55*(1+P$3)^1 -> 45312399 | S55: =+P55*(1+S$3)^1 -> 47964524
B56: 2 | C56: Asistente de IA mensual | D56: mes | E56: 600000 | F56: =+E56*12 -> 7200000 | G56: =+F56*(1+G$3) -> 7644312 | J56: =+G56*(1+J$3) -> 8086038.6 | M56: =+J56*(1+M$3)^1 -> 8558469.4 | P56: =+M56*(1+P$3)^1 -> 9062479.8 | S56: =+P56*(1+S$3)^1 -> 9592904.7
B57: 3 | C57: Servicios públicos e internet | D57: mes | E57: 700000 | F57: =+E57*12 -> 8400000 | G57: =+F57*(1+G$3) -> 8918364 | J57: =+G57*(1+J$3) -> 9433711.7 | M57: =+J57*(1+M$3)^1 -> 9984881 | P57: =+M57*(1+P$3)^1 -> 10572893 | S57: =+P57*(1+S$3)^1 -> 11191722
B58: 4 | C58: Mantenimiento y limpieza | D58: mes | E58: 350000 | F58: =+E58*12 -> 4200000 | G58: =+F58*(1+G$3) -> 4459182 | J58: =+G58*(1+J$3) -> 4716855.8 | M58: =+J58*(1+M$3)^1 -> 4992440.5 | P58: =+M58*(1+P$3)^1 -> 5286446.6 | S58: =+P58*(1+S$3)^1 -> 5595861.1
B59: 5 | C59: Hosting, dominio, SSL y mantenimiento mensual | D59: mes | E59: 120000 | F59: =+E59*12 -> 1440000 | G59: =+F59*(1+G$3) -> 1528862.4 | J59: =+G59*(1+J$3) -> 1617207.7 | M59: =+J59*(1+M$3)^1 -> 1711693.9 | P59: =+M59*(1+P$3)^1 -> 1812496 | S59: =+P59*(1+S$3)^1 -> 1918580.9
B60: 6 | C60: Arriendo | D60: mes | E60: 1900000 | F60: =+E60*12 -> 22800000 | G60: =+F60*(1+G$3) -> 24206988 | J60: =+G60*(1+J$3) -> 25605789 | M60: =+J60*(1+M$3)^1 -> 27101820 | P60: =+M60*(1+P$3)^1 -> 28697853 | S60: =+P60*(1+S$3)^1 -> 30377532
B61: 7 | C61: Dotación y seguridad | D61: mes | E61: 1000000 | F61: =+E61*12 -> 12000000 | G61: =+F61*(1+G$3) -> 12740520 | J61: =+G61*(1+J$3) -> 13476731 | M61: =+J61*(1+M$3)^1 -> 14264116 | P61: =+M61*(1+P$3)^1 -> 15104133 | S61: =+P61*(1+S$3)^1 -> 15988175
B62: 8 | C62: Comision Integración con pasarelas de pago y logística | D62: mes | E62: =+('PROYECCIONES Y ESTIMACIONES'!D6*'ESTUDIO FINANCIERO'!D21)*0.028 -> 4.7048131e+08 | F62: =+E62*12 -> 5.6457757e+09 | G62: =+F62*(1+G$3) -> 5.9941765e+09 | J62: =+G62*(1+J$3) -> 6.34055e+09 | M62: =+J62*(1+M$3)^1 -> 6.7109998e+09 | P62: =+M62*(1+P$3)^1 -> 7.1062122e+09 | S62: =+P62*(1+S$3)^1 -> 7.5221373e+09
B63: 9 | C63: Publicidad digital | D63: año | E63: Valor sin sumar, solo para proyectar | F63: 12000000 | G63: =+F63*(1+G$3) -> 12740520 | J63: =+G63*(1+J$3) -> 13476731 | M63: =+J63*(1+M$3)^1 -> 14264116 | P63: =+M63*(1+P$3)^1 -> 15104133 | S63: =+P63*(1+S$3)^1 -> 15988175
B64: 10 | C64: Contenido y fidelización | D64: año | F64: 8000000 | G64: =+F64*(1+G$3) -> 8493680 | J64: =+G64*(1+J$3) -> 8984487.3 | M64: =+J64*(1+M$3)^1 -> 9509410.5 | P64: =+M64*(1+P$3)^1 -> 10069422 | S64: =+P64*(1+S$3)^1 -> 10658783
V65: Total
F66: =+SUM(F55:F62) -> 5.7378157e+09 | G66: Total Costos fijos | I66: =SUM(G55:G62) -> 6.0918963e+09 | J66: Total Costos fijos | L66: =SUM(J55:J64) -> 6.4663777e+09 | M66: Total Costos fijos | O66: =SUM(M55:M64) -> 6.8441791e+09 | P66: Total Costos fijos | R66: =SUM(P55:P64) -> 7.2472345e+09 | S66: Total Costos fijos | U66: =SUM(S55:S64) -> 7.6714135e+09 | V66: =+SUM(I66+L66+O66+R66+U66) -> 3.4321101e+10
C68: Gastos administrativos | G68: =+'GASTOS ADMINISTRATIVOS'!H13 -> 3.512907e+08 | J68: =+'GASTOS ADMINISTRATIVOS'!J13 -> 6.6508576e+08 | M68: =+'GASTOS ADMINISTRATIVOS'!L13 -> 7.3760671e+08 | P68: =+'GASTOS ADMINISTRATIVOS'!N13 -> 8.1937779e+08 | S68: =+'GASTOS ADMINISTRATIVOS'!P13 -> 9.0972403e+08 | V68: =+SUM(G68+J68+M68+P68+S68) -> 3.483085e+09

Sheet GASTOS ADMINISTRATIVOS
H2: Aumento salarial
H3: =+'PROYECCIONES Y ESTIMACIONES'!Q8 -> 0.1158 | J3: =+'PROYECCIONES Y ESTIMACIONES'!Q9 -> 0.1106 | L3: =+'PROYECCIONES Y ESTIMACIONES'!Q10 -> 0.10904 | N3: =+'PROYECCIONES Y ESTIMACIONES'!Q11 -> 0.11086 | P3: =+'PROYECCIONES Y ESTIMACIONES'!Q12 -> 0.110262
B4: NOMINA
B5: Cargos | C5: Salario estimado | D5: Salario neto | E5: # | F5: Año 0 | G5: # | H5: Año 1 | I5: # | J5: Año 2 | K5: # | L5: Año 3 | M5: # | N5: Año 4 | O5: # | P5: Año 5
B6: Gerente general | C6: 3673786 | D6: 5395151 | E6: 1 | F6: =+D6*E6*12 -> 64741812 | G6: 1 | H6: =+($D6*G6*12)*(1+H$3) -> 72238914 | I6: ='PROYECCIONES Y ESTIMACIONES'!E10 -> 1 | J6: =+($D6*I6*12)*(1+H$3)*(1+J$3) -> 80228538 | K6: ='PROYECCIONES Y ESTIMACIONES'!F10 -> 1 | L6: =+($D6*K6*12)*(1+H$3)*(1+J$3)*(1+L$3) -> 88976657 | M6: ='PROYECCIONES Y ESTIMACIONES'!G10 -> 1 | N6: =+($D6*M6*12)*(1+H$3)*(1+J$3)*(1+L$3)*(1+N$3) -> 98840610 | O6: ='PROYECCIONES Y ESTIMACIONES'!H10 -> 1 | P6: =+($D6*O6*12)*(1+H$3)*(1+J$3)*(1+L$3)*(1+N$3)*(1+P$3) -> 1.0973897e+08
B7: Contador | C7: 2582448 | D7: 4027796 | E7: 1 | F7: =+D7*E7*12 -> 48333552 | G7: 1 | H7: =+($D7*G7*12)*(1+H$3) -> 53930577 | I7: ='PROYECCIONES Y ESTIMACIONES'!E11 -> 2 | J7: =+($D7*I7*12)*(1+H$3)*(1+J$3) -> 1.197906e+08 | K7: ='PROYECCIONES Y ESTIMACIONES'!F11 -> 2 | L7: =+($D7*K7*12)*(1+H$3)*(1+J$3)*(1+L$3) -> 1.3285257e+08 | M7: ='PROYECCIONES Y ESTIMACIONES'!G11 -> 2 | N7: =+($D7*M7*12)*(1+H$3)*(1+J$3)*(1+L$3)*(1+N$3) -> 1.475806e+08 | O7: ='PROYECCIONES Y ESTIMACIONES'!H11 -> 2 | P7: =+($D7*O7*12)*(1+H$3)*(1+J$3)*(1+L$3)*(1+N$3)*(1+P$3) -> 1.6385313e+08
B8: Encargado de bodega | C8: 1584652 | D8: 2562479 | E8: 1 | F8: =+D8*E8*12 -> 30749748 | G8: 1 | H8: =+($D8*G8*12)*(1+H$3) -> 34310569 | I8: ='PROYECCIONES Y ESTIMACIONES'!E12 -> 2 | J8: =+($D8*I8*12)*(1+H$3)*(1+J$3) -> 76210635 | K8: ='PROYECCIONES Y ESTIMACIONES'!F12 -> 2 | L8: =+($D8*K8*12)*(1+H$3)*(1+J$3)*(1+L$3) -> 84520643 | M8: ='PROYECCIONES Y ESTIMACIONES'!G12 -> 2 | N8: =+($D8*M8*12)*(1+H$3)*(1+J$3)*(1+L$3)*(1+N$3) -> 93890602 | O8: ='PROYECCIONES Y ESTIMACIONES'!H12 -> 2 | P8: =+($D8*O8*12)*(1+H$3)*(1+J$3)*(1+L$3)*(1+N$3)*(1+P$3) -> 1.0424317e+08
B9: Operario de bodega | C9: 1423500 | D9: 2325819 | E9: 1 | F9: =+D9*E9*12 -> 27909828 | G9: 1 | H9: =+($D9*G9*12)*(1+H$3) -> 31141786 | I9: ='PROYECCIONES Y ESTIMACIONES'!E13 -> 2 | J9: =+($D9*I9*12)*(1+H$3)*(1+J$3) -> 69172135 | K9: ='PROYECCIONES Y ESTIMACIONES'!F13 -> 2 | L9: =+($D9*K9*12)*(1+H$3)*(1+J$3)*(1+L$3) -> 76714665 | M9: ='PROYECCIONES Y ESTIMACIONES'!G13 -> 2 | N9: =+($D9*M9*12)*(1+H$3)*(1+J$3)*(1+L$3)*(1+N$3) -> 85219253 | O9: ='PROYECCIONES Y ESTIMACIONES'!H13 -> 2 | P9: =+($D9*O9*12)*(1+H$3)*(1+J$3)*(1+L$3)*(1+N$3)*(1+P$3) -> 94615698
B10: Encargado de TI | C10: 3333483 | D10: 4895398 | E10: 1 | F10: =+D10*E10*12 -> 58744776 | G10: 1 | H10: =+($D10*G10*12)*(1+H$3) -> 65547421 | I10: ='PROYECCIONES Y ESTIMACIONES'!E14 -> 2 | J10: =+($D10*I10*12)*(1+H$3)*(1+J$3) -> 1.4559393e+08 | K10: ='PROYECCIONES Y ESTIMACIONES'!F14 -> 2 | L10: =+($D10*K10*12)*(1+H$3)*(1+J$3)*(1+L$3) -> 1.6146949e+08 | M10: ='PROYECCIONES Y ESTIMACIONES'!G14 -> 2 | N10: =+($D10*M10*12)*(1+H$3)*(1+J$3)*(1+L$3)*(1+N$3) -> 1.7937e+08 | O10: ='PROYECCIONES Y ESTIMACIONES'!H14 -> 2 | P10: =+($D10*O10*12)*(1+H$3)*(1+J$3)*(1+L$3)*(1+N$3)*(1+P$3) -> 1.991477e+08
B11: Asesor en linea | C11: 1441200 | D11: 2351812 | E11: 2 | F11: =+D11*E11*12 -> 56443488 | G11: 2 | H11: =+($D11*G11*12)*(1+H$3) -> 62979644 | I11: ='PROYECCIONES Y ESTIMACIONES'!E15 -> 3 | J11: =+($D11*I11*12)*(1+H$3)*(1+J$3) -> 1.0491779e+08 | K11: ='PROYECCIONES Y ESTIMACIONES'!F15 -> 3 | L11: =+($D11*K11*12)*(1+H$3)*(1+J$3)*(1+L$3) -> 1.1635802e+08 | M11: ='PROYECCIONES Y ESTIMACIONES'!G15 -> 3 | N11: =+($D11*M11*12)*(1+H$3)*(1+J$3)*(1+L$3)*(1+N$3) -> 1.2925748e+08 | O11: ='PROYECCIONES Y ESTIMACIONES'!H15 -> 3 | P11: =+($D11*O11*12)*(1+H$3)*(1+J$3)*(1+L$3)*(1+N$3)*(1+P$3) -> 1.4350966e+08
B12: Aseadora | C12: 1423500 | D12: 2325819 | E12: 1 | F12: =+D12*E12*12 -> 27909828 | G12: 1 | H12: =+($D12*G12*12)*(1+H$3) -> 31141786 | I12: ='PROYECCIONES Y ESTIMACIONES'!E16 -> 2 | J12: =+($D12*I12*12)*(1+H$3)*(1+J$3) -> 69172135 | K12: ='PROYECCIONES Y ESTIMACIONES'!F16 -> 2 | L12: =+($D12*K12*12)*(1+H$3)*(1+J$3)*(1+L$3) -> 76714665 | M12: ='PROYECCIONES Y ESTIMACIONES'!G16 -> 2 | N12: =+($D12*M12*12)*(1+H$3)*(1+J$3)*(1+L$3)*(1+N$3) -> 85219253 | O12: ='PROYECCIONES Y ESTIMACIONES'!H16 -> 2 | P12: =+($D12*O12*12)*(1+H$3)*(1+J$3)*(1+L$3)*(1+N$3)*(1+P$3) -> 94615698
B13: Total | D13: =+SUM(D6:D12) -> 23884274 | E13: =+SUM(E6:E12) -> 8 | F13: =+SUM(F6:F12) -> 314833032 | G13: =+SUM(G6:G12) -> 8 | H13: =+SUM(H6:H12) -> 3.512907e+08 | I13: =+SUM(I6:I12) -> 14 | J13: =+SUM(J6:J12) -> 6.6508576e+08 | K13: =+SUM(K6:K12) -> 14 | ... P13: =+SUM(P6:P12) -> 9.0972403e+08

Sheet ESTUDIO FINANCIERO
B2: Evaluación Financiera
B3: Título del proyecto | C3: Perfumes Aria | D3: Unidades de análisis
B4: Fecha de realización | C4: 45981 | D4: Pesos colombianos
B6: Tabla 1. Inflación proyectada
B7: Año | C7: Inflación Proyectada
B8: =+D17 -> 1 | C8: =+'PROYECCIONES Y ESTIMACIONES'!M8 -> 0.06171
B9: =+B8+1 -> 2 | C9: =+'PROYECCIONES Y ESTIMACIONES'!M9 -> 0.057785
B10: =+B9+1 -> 3 | C10: =+'PROYECCIONES Y ESTIMACIONES'!M10 -> 0.0584255
B11: =+B10+1 -> 4 | C11: =+'PROYECCIONES Y ESTIMACIONES'!M11 -> 0.05889025
B12: =+B11+1 -> 5 | C12: =+'PROYECCIONES Y ESTIMACIONES'!M12 -> 0.058529775 | K12: =+K14*(1+L12) -> 676200 | L12: 0.38
K13: =+K14*(1+L13) -> 588000 | L13: 0.2
B14: Tabla 2. Ingresos operacionales | K14: 490000 | L14: 0
B15: INGRESOS OPERACIONALES Y NO OPERACIONALES | K15: =+K14*(1+L15) -> 392000 | L15: -0.2
C16: =+D4 -> Pesos colombianos | K16: 305253.25 | L16: =+(K16-K14)/K14 -> -0.37703418
B17: Año | C17: 0 | D17: =+C17+1 -> 1 | E17: =+D17+1 -> 2 | F17: =+E17+1 -> 3 | G17: =+F17+1 -> 4 | H17: =+G17+1 -> 5
B18: Capacidad de produccion | D18: 390000 | E18: =+'PROYECCIONES Y ESTIMACIONES'!E4 -> 409500 | F18: =+'PROYECCIONES Y ESTIMACIONES'!F4 -> 429975 | G18: =+'PROYECCIONES Y ESTIMACIONES'!G4 -> 451474 | H18: =+'PROYECCIONES Y ESTIMACIONES'!H4 -> 474048
B19: % de utilizacion de la capacidad | D19: 0.8 | E19: =+D19 -> 0.8 | F19: 1 | G19: 1 | H19: 1
B20: Producción (und/año) | D20: =+D18*D19 -> 312000 | E20: =+E18*E19 -> 327600 | F20: =+F18*F19 -> 429975 | G20: =+G18*G19 -> 451474 | H20: =+H18*H19 -> 474048
B21: Precio venta ($/und) | C21: 347830 | D21: =+C21*(1+C8) -> 369294.59 | E21: =+D21*(1+C9) -> 390634.28 | F21: =+E21*(1+C10) -> 413457.28 | G21: =+F21*(1+C11) -> 437805.88 | H21: =+G21*(1+C12) -> 463430.56
B22: Total Ingresos operacionales | C22: 0 | D22: =+D20*D21 -> 1.1521991e+11 | E22: =+E20*E21 -> 1.2797179e+11 | F22: =+F20*F21 -> 1.7777629e+11 | G22: =+G20*G21 -> 1.9765797e+11 | H22: =+H20*H21 -> 2.1968833e+11
B24: Tabla 3. Inversiones
B25: INVERSIONES
B26: Año | C26: 0 | D26: =+C26+1 -> 1 | E26: =+D26+1 -> 2 | F26: =+E26+1 -> 3 | G26: =+F26+1 -> 4 | H26: =+G26+1 -> 5
B27: Activos fijos depreciables | C27: =+SUM('CALCULO COSTOS E INVERSIONES'!G9:G24) -> 30705000 | D27: =+SUM('CALCULO COSTOS E INVERSIONES'!J9:J23) -> 0 | E27: =+SUM('CALCULO COSTOS E INVERSIONES'!M9:M23) -> 11674218 | F27: =+SUM('CALCULO COSTOS E INVERSIONES'!P9:P23) -> 0 | G27: =+SUM('CALCULO COSTOS E INVERSIONES'!S9:S23) -> 0 | H27: =+SUM('CALCULO COSTOS E INVERSIONES'!V9:V23) -> 2398226.2
B28: Activos diferidos | C28: =+SUM('CALCULO COSTOS E INVERSIONES'!G25:G29) -> 40000000 | D28: 0 | E28: 0 | F28: 0 | G28: 0 | H28: 0
B29: Terrenos | C29: 0 | D29: 0 | E29: 0 | F29: 0 | G29: 0
B30: Capital de trabajo | C30: =+C43 -> 0 | D30: =+D44 -> 9.4260133e+09 | E30: =+E44 -> 9.682833e+08 | F30: =+F44 -> 1.2199661e+09 | G30: =+G44 -> 1.2082941e+09 | H30: =+H44 -> 1.3332695e+09
B31: Total inversión | C31: =+SUM(C27:C30) -> 70705000 | D31: =+SUM(D27:D30) -> 9.4260133e+09 | E31: =+SUM(E27:E30) -> 9.7995752e+08 | F31: =+SUM(F27:F30) -> 1.2199661e+09 | G31: =+SUM(G27:G30) -> 1.2082941e+09 | H31: =+SUM(H27:H30) -> 1.3356677e+09
B33: Capital de trabajo neto por el método contable
B34: Año | C34: 0 | D34: =+C34+1 -> 1 | E34: =+D34+1 -> 2 | F34: =+E34+1 -> 3 | G34: =+F34+1 -> 4 | H34: =+G34+1 -> 5
B35: Dias Efectivo | C35: 90 | D35: =+C35 -> 90 | E35: =+D35 -> 90 | F35: =+E35 -> 90 | G35: =+F35 -> 90 | H35: =+G35 -> 90
B36: Efectivo | C36: =+(C56/360)*C35 -> 0 | D36: =+(D56/360)*D35 -> 1.5229741e+09 | E36: =+(E56/360)*E35 -> 1.6165944e+09 | F36: =+(F56/360)*F35 -> 1.7110448e+09 | G36: =+(G56/360)*G35 -> 1.8118086e+09 | H36: =+(H56/360)*H35 -> 1.9178534e+09
B37: Dias inventario | C37: 30 | D37: =+C37 -> 30 | E37: =+D37 -> 30 | F37: =+E37 -> 30 | G37: =+F37 -> 30 | H37: =+G37 -> 30
B38: Inventario | C38: =+(C55/360)*C37 -> 0 | D38: =+(D55/360)*D37 -> 9.6821169e+09 | E38: =+(E55/360)*E37 -> 1.0753678e+10 | F38: =+(F55/360)*F37 -> 1.1951065e+10 | G38: =+(G55/360)*G37 -> 1.3287617e+10 | H38: =+(H55/360)*H37 -> 1.4768615e+10
B39: Dias CXC | C39: 1.5 | D39: =+C39 -> 1.5 | E39: =+D39 -> 1.5 | F39: =+E39 -> 1.5 | G39: =+F39 -> 1.5 | H39: =+G39 -> 1.5
B40: CXC | C40: =+(C22/360)*C39 -> 0 | D40: =+(D22/360)*D39 -> 4.8008297e+08 | E40: =+(E22/360)*E39 -> 5.3321579e+08 | F40: =+(F22/360)*F39 -> 7.4073456e+08 | G40: =+(G22/360)*G39 -> 8.2357489e+08 | H40: =+(H22/360)*H39 -> 9.1536805e+08
B41: Dias proveedores | C41: 7 | D41: =+C41 -> 7 | E41: =+D41 -> 7 | F41: =+E41 -> 7 | G41: =+F41 -> 7 | H41: =+G41 -> 7
B42: CXP | C42: =+(C55/360)*C41 -> 0 | D42: =+(D55/360)*D41 -> 2.2591606e+09 | E42: =+(E55/360)*E41 -> 2.5091915e+09 | F42: =+(F55/360)*F41 -> 2.7885819e+09 | G42: =+(G55/360)*G41 -> 3.100444e+09 | H42: =+(H55/360)*H41 -> 3.4460102e+09
B43: Capital de trabajo | C43: =+C36+C38+C40-C42 -> 0 | D43: =+D36+D38+D40-D42 -> 9.4260133e+09 | E43: =+E36+E38+E40-E42 -> 1.0394297e+10 | F43: =+F36+F38+F40-F42 -> 1.1614263e+10 | G43: =+G36+G38+G40-G42 -> 1.2822557e+10 | H43: =+H36+H38+H40-H42 -> 1.4155826e+10
B44: Variacion | D44: =+D43-C43 -> 9.4260133e+09 | E44: =+E43-D43 -> 9.682833e+08 | F44: =+F43-E43 -> 1.2199661e+09 | G44: =+G43-F43 -> 1.2082941e+09 | H44: =+H43-G43 -> 1.3332695e+09
B46: Tabla 4. Datos para el cálculo de la depreciación y amortización de activos
B47: Datos para cálculo de depreciación y amortización de activos
B48: Vida útil activos depreciables (años | C48: 5 y 10
B49: Periodo amortización diferidos e intangibles (años) | C49: 5
B51: Tabla 5. Datos apra el cálculo de los egresos
B52: DATOS PARA EL CÁLCULO DE EGRESOS
B53: Año | C53: 0 | D53: 1 | E53: 2 | F53: 3 | G53: 4 | H53: 5
B54: Costo variable unitario ($/kg) | C54: =+'PROYECCIONES Y ESTIMACIONES'!R18 -> 267561.11 | D54: =+C54*(1+C8) -> 284072.31 | E54: =+D54*(1+C9) -> 300487.43 | F54: =+E54*(1+C10) -> 318043.55 | G54: =+F54*(1+C11) -> 336773.22 | H54: =+G54*(1+C12) -> 356484.48
B55: Costos variables totales (millones de pesos) | C55: 0 | D55: =+'CALCULO COSTOS E INVERSIONES'!I49 -> 1.161854e+11 | E55: =+'CALCULO COSTOS E INVERSIONES'!L49 -> 1.2904413e+11 | F55: =+'CALCULO COSTOS E INVERSIONES'!O49 -> 1.4341278e+11 | G55: =+'CALCULO COSTOS E INVERSIONES'!R49 -> 1.5945141e+11 | H55: =+'CALCULO COSTOS E INVERSIONES'!U49 -> 1.7722338e+11
B56: Costos fijos por año | C56: 0 | D56: =+'CALCULO COSTOS E INVERSIONES'!I66 -> 6.0918963e+09 | E56: =+'CALCULO COSTOS E INVERSIONES'!L66 -> 6.4663777e+09 | F56: =+'CALCULO COSTOS E INVERSIONES'!O66 -> 6.8441791e+09 | G56: =+'CALCULO COSTOS E INVERSIONES'!R66 -> 7.2472345e+09 | H56: =+'CALCULO COSTOS E INVERSIONES'!U66 -> 7.6714135e+09
B57: Gastos de administración y ventas | C57: 0 | D57: =+'GASTOS ADMINISTRATIVOS'!H13 -> 3.512907e+08 | E57: =+'GASTOS ADMINISTRATIVOS'!J13 -> 6.6508576e+08 | F57: =+'GASTOS ADMINISTRATIVOS'!L13 -> 7.3760671e+08 | G57: =+'GASTOS ADMINISTRATIVOS'!N13 -> 8.1937779e+08 | H57: =+'GASTOS ADMINISTRATIVOS'!P13 -> 9.0972403e+08
B58: Vlr de rescate (millones de pesos corrientes) | C58: =+G64 -> 5625000
B60: Valor de rescate por el método de calculo contable
C61: Valor Activo | D61: Años de depreciacion | E61: Depreciacion Anual | F61: Años evaluacion | G61: Valor de desecho
B62: Activos fijos depreciables a 5 años | C62: =+('CALCULO COSTOS E INVERSIONES'!G9+'CALCULO COSTOS E INVERSIONES'!G10+'CALCULO COSTOS E INVERSIONES'!G12+'CALCULO COSTOS E INVERSIONES'!G14+'CALCULO COSTOS E INVERSIONES'!G15+'CALCULO COSTOS E INVERSIONES'!G16+'CALCULO COSTOS E INVERSIONES'!G18+'CALCULO COSTOS E INVERSIONES'!G19+'CALCULO COSTOS E INVERSIONES'!G22+'CALCULO COSTOS E INVERSIONES'!G23+'CALCULO COSTOS E INVERSIONES'!G24) -> 19455000 | D62: 5 | E62: =+C62/D62 -> 3891000 | F62: 5 | G62: =+C62-(E62*F62) -> 0
B63: Activos fijos depreciables a 10 años | C63: =+('CALCULO COSTOS E INVERSIONES'!G11+'CALCULO COSTOS E INVERSIONES'!G13+'CALCULO COSTOS E INVERSIONES'!G17+'CALCULO COSTOS E INVERSIONES'!G20+'CALCULO COSTOS E INVERSIONES'!G21) -> 11250000 | D63: 10 | E63: =+C63/D63 -> 1125000 | F63: 5 | G63: =+C63-(E63*F63) -> 5625000
F64: Valor de rescate | G64: =+SUM(G63:G63) -> 5625000
B66: Tabla 6. Datos para el cálculo de la financiación
B67: FINANCIACIÓN
B68: Préstamo (millones) | C68: 50000000
B69: Interés efectivo | C69: 0.2489 | D69: EA
B70: Forma de pago | C70: Cinco cuotas iguales
B71: Número de cuotas | C71: 5
B73: Tabla 7. Tarifa impositiva
B74: IMPUESTOS
B75: Impuesto de renta (%) | C75: 0.35
B77: Tabla 8. Cálculo de los costos de oportunidad
B78: COSTO DE OPORTUNIDAD
B79: Costo de oportunidad en térnimos nominales | C79: 0.15
B80: Porcentaje financiado con recursos propios | C80: =+(C31-C68)/C31 -> 0.29283643
B81: Costo de la deuda d.d.i (k.d.d.i=Kd(1-t)) | C81: =+C69*(1-C75) -> 0.161785
B82: CCP ddi en términos nominales | C82: =+(C80*C79)+(1-C80)*C81 -> 0.15833392
B84: Tabla 9. | F84: Tabla 10
B85: Depreciación | F85: Amortización de Inversiones
B86: Millones de pesos | F86: Millones de pesos
B87: Fin Año | C87: Depreciación anual ( 5 años ) | D87: Depreciación anual ( 10 años ) | F87: Fin Año | G87: Amortización anual pesos corrientes
B88: 1 | C88: =+('CALCULO COSTOS E INVERSIONES'!G9+'CALCULO COSTOS E INVERSIONES'!G10+'CALCULO COSTOS E INVERSIONES'!G12+'CALCULO COSTOS E INVERSIONES'!G14+'CALCULO COSTOS E INVERSIONES'!G15+'CALCULO COSTOS E INVERSIONES'!G16+'CALCULO COSTOS E INVERSIONES'!G18+'CALCULO COSTOS E INVERSIONES'!G19+'CALCULO COSTOS E INVERSIONES'!G22+'CALCULO COSTOS E INVERSIONES'!G23+'CALCULO COSTOS E INVERSIONES'!G24)/5 -> 3891000 | D88: =+('CALCULO COSTOS E INVERSIONES'!G11+'CALCULO COSTOS E INVERSIONES'!G13+'CALCULO COSTOS E INVERSIONES'!G17+'CALCULO COSTOS E INVERSIONES'!G20+'CALCULO COSTOS E INVERSIONES'!G21)/10 -> 1125000 | F88: 1 | G88: =+(C28-25000000)/C49 -> 3000000
B89: 2 | C89: =+C88 -> 3891000 | D89: =+D88 -> 1125000 | F89: 2 | G89: =+G88 -> 3000000
B90: 3 | C90: =+C89 -> 3891000 | D90: =+D89 -> 1125000 | F90: 3 | G90: =+G89 -> 3000000
B91: 4 | C91: =+C90 -> 3891000 | D91: =+D90 -> 1125000 | F91: 4 | G91: =+G90 -> 3000000
B92: 5 | C92: =+C91 -> 3891000 | D92: =+D91 -> 1125000 | F92: 5 | G92: =+G91 -> 3000000
B94: Tabla 11
B95: Flujo de caja proyectado para el calculo de la TIR y VPN del proyecto puro despues de impuestos
B96: 0
B97: Concepto | C97: 0 | D97: 1 | E97: 2 | F97: 3 | G97: 4 | H97: 5
B98: +Ingresos por ventas | C98: 0 | D98: =+D22 -> 1.1521991e+11 | E98: =+E22 -> 1.2797179e+11 | F98: =+F22 -> 1.7777629e+11 | G98: =+G22 -> 1.9765797e+11 | H98: =+H22 -> 2.1968833e+11
B99: - Costo de producción variable | C99: 0 | D99: =+D55 -> 1.161854e+11 | E99: =+E55 -> 1.2904413e+11 | F99: =+F55 -> 1.4341278e+11 | G99: =+G55 -> 1.5945141e+11 | H99: =+H55 -> 1.7722338e+11
B100: - Costo de producción fijo | C100: 0 | D100: =+D56 -> 6.0918963e+09 | E100: =+E56 -> 6.4663777e+09 | F100: =+F56 -> 6.8441791e+09 | G100: =+G56 -> 7.2472345e+09 | H100: =+H56 -> 7.6714135e+09
B101: - Gastos de administración y ventas | C101: 0 | D101: =+D57 -> 3.512907e+08 | E101: =+E57 -> 6.6508576e+08 | F101: =+F57 -> 7.3760671e+08 | G101: =+G57 -> 8.1937779e+08 | H101: =+H57 -> 9.0972403e+08
B102: = Renta bruta | C102: =+C98-(C99+C100+C101) -> 0 | D102: =+D98-(D99+D100+D101) -> -7.4086777e+09 | E102: =+E98-(E99+E100+E101) -> -8.2038092e+09 | F102: =+F98-(F99+F100+F101) -> 2.6781725e+10 | G102: =+G98-(G99+G100+G101) -> 3.0139953e+10 | H102: =+H98-(H99+H100+H101) -> 3.3883813e+10
B103: -Amortización intangibles | C103: 0 | D103: =+G88 -> 3000000 | E103: =+D103 -> 3000000 | F103: =+E103 -> 3000000 | G103: =+F103 -> 3000000 | H103: =+G103 -> 3000000
B104: -Depreciación | C104: 0 | D104: =+C88+D88 -> 5016000 | E104: =+D104 -> 5016000 | F104: =+E104 -> 5016000 | G104: =+F104 -> 5016000 | H104: =+G104 -> 5016000
B105: = Renta Líquida Gravable (RLG) | C105: =+C102-C103-C104 -> 0 | D105: =+D102-D103-D104 -> -7.4166937e+09 | E105: =+E102-E103-E104 -> -8.2118252e+09 | F105: =+F102-F103-F104 -> 2.6773709e+10 | G105: =+G102-G103-G104 -> 3.0131937e+10 | H105: =+H102-H103-H104 -> 3.3875797e+10
B106: -Impuesto de renta | D106: 0 | E106: 0 | F106: =+F105*$C$75 -> 9.3707982e+09 | G106: =+G105*$C$75 -> 1.0546178e+10 | H106: =+H105*$C$75 -> 1.1856529e+10
B107: +Amortización intangibles | D107: =+D103 -> 3000000 | E107: =+E103 -> 3000000 | F107: =+F103 -> 3000000 | G107: =+G103 -> 3000000 | H107: =+H103 -> 3000000
B108: +Depreciación | D108: =+D104 -> 5016000 | E108: =+E104 -> 5016000 | F108: =+F104 -> 5016000 | G108: =+G104 -> 5016000 | H108: =+H104 -> 5016000
B109: -Activos depreciables | C109: =+C27 -> 30705000 | D109: =+D27 -> 0 | E109: =+E27 -> 11674218 | F109: =+F27 -> 0 | G109: =+G27 -> 0 | H109: =+H27 -> 2398226.2
B110: -Activos Diferidos | C110: =+C28 -> 40000000 | D110: =+D28 -> 0 | E110: =+E28 -> 0 | F110: =+F28 -> 0 | G110: =+G28 -> 0 | H110: =+H28 -> 0
B111: -Terrenos | C111: =+C29 -> 0 | D111: 0 | E111: 0 | F111: 0 | G111: 0 | H111: 0
B112: -Capital de Trabajo | C112: =+C30 -> 0 | D112: =+D30 -> 9.4260133e+09 | E112: =+E30 -> 9.682833e+08 | F112: =+F30 -> 1.2199661e+09 | G112: =+G30 -> 1.2082941e+09 | H112: =+H30 -> 1.3332695e+09
...

Sheet ANÁLISIS-SENSIBILIDAD
B2: Resumen del escenario
D3: Valores actuales: | E3: 0.2 | F3: 0.1 | G3: Inicial | H3: Critico | I3: -0.1
E4: Creado por Juan Manuel Arredondo Londoño el 28/11/2025 | F4: Creado por Juan Manuel Arredondo Londoño el 28/11/2025 | G4: Creado por Juan Manuel Arredondo Londoño el 28/11/2025 | H4: Creado por Juan Manuel Arredondo Londoño el 28/11/2025 Modificado por Juan Manuel Arredondo Londoño el 28/11/2025 | I4: Creado por Juan Manuel Arredondo Londoño el 28/11/2025
B5: Celdas cambiantes:
C6: Precio | D6: 347830 | E6: 417396 | F6: 382613 | G6: 347830 | H6: 334311.66 | I6: 313047
B7: Celdas de resultado:
C8: Tir Ind | D8: 0.41204965 | E8: 296.04509 | F8: 2.1462434 | G8: 0.41204965 | H8: 0.15833392 | I8: -0.14785463
C9: VPN | D9: 1.5888098e+10 | E9: 9.7648997e+10 | F9: 5.6768548e+10 | G9: 1.5888098e+10 | H9: 0.00068034232 | I9: -2.4992351e+10
B36: Resumen del escenario
D37: Valores actuales: | E37: 0.15 | F37: 0.1 | G37: % Inicial | H37: % Critico | I37: -0.1 | J37: -0.15
B38: Celdas cambiantes:
C39: % Utilidad | D39: 0.8 | E39: 0.95 | F39: 0.9 | G39: 0.8 | H39: 0.73473005 | I39: 0.7 | J39: 0.65
B40: Celdas de resultado:
C41: Tir Ind | D41: 0.41204965 | E41: 227.23277 | F41: 3.492452 | G41: 0.41204965 | H41: 0.15833392 | I41: 0.076116201 | J41: -0.011526887
C42: VPN | D42: 1.5888098e+10 | E42: 5.2401298e+10 | F42: 4.0230232e+10 | G42: 1.5888098e+10 | H42: 3.4864992e-05 | I42: -8.4540354e+09 | J42: -2.0625102e+10

Sheet ESTUDIO FINANCIERO (2)
B2: Evaluación Financiera
B3: Título del proyecto | C3: Perfumes Aria | D3: Unidades de análisis
B4: Fecha de realización | C4: 45981 | D4: Pesos colombianos
B6: Tabla 1. Inflación proyectada
B7: Año | C7: Inflación Proyectada
B8: =+D17 -> 1 | C8: =+'PROYECCIONES Y ESTIMACIONES'!M8 -> 0.06171
B9: =+B8+1 -> 2 | C9: =+'PROYECCIONES Y ESTIMACIONES'!M9 -> 0.057785
B10: =+B9+1 -> 3 | C10: =+'PROYECCIONES Y ESTIMACIONES'!M10 -> 0.0584255
B11: =+B10+1 -> 4 | C11: =+'PROYECCIONES Y ESTIMACIONES'!M11 -> 0.05889025 | F11: Precio de venta critico | G11: 334311.66 | H11: El proyecto puede resistir el cambio en el precio en hasta un 3,8% dejando este de ser atractivo para la inversión.
B12: =+B11+1 -> 5 | C12: =+'PROYECCIONES Y ESTIMACIONES'!M12 -> 0.058529775 | F12: % de utilización de la capacidad | G12: 0.73473005
B14: Tabla 2. Ingresos operacionales
B15: INGRESOS OPERACIONALES Y NO OPERACIONALES
C16: =+D4 -> Pesos colombianos
B17: Año | C17: 0 | D17: =+C17+1 -> 1 | E17: =+D17+1 -> 2 | F17: =+E17+1 -> 3 | G17: =+F17+1 -> 4 | H17: =+G17+1 -> 5 | M17: 0.1
B18: Capacidad de produccion | D18: 390000 | E18: =+'PROYECCIONES Y ESTIMACIONES'!E4 -> 409500 | F18: =+'PROYECCIONES Y ESTIMACIONES'!F4 -> 429975 | G18: =+'PROYECCIONES Y ESTIMACIONES'!G4 -> 451474 | H18: =+'PROYECCIONES Y ESTIMACIONES'!H4 -> 474048
B19: % de utilizacion de la capacidad | D19: 0.8 | E19: =+D19 -> 0.8 | F19: 1 | G19: 1 | H19: 1
B20: Producción (und/año) | D20: =+D18*D19 -> 312000 | E20: =+E18*E19 -> 327600 | F20: =+F18*F19 -> 429975 | G20: =+G18*G19 -> 451474 | H20: =+H18*H19 -> 474048 | J20: +20% | K20: =K22*1.2 -> 417396
B21: Precio venta ($/und) | C21: 347830 | D21: =+C21*(1+C8) -> 369294.59 | E21: =+D21*(1+C9) -> 390634.28 | F21: =+E21*(1+C10) -> 413457.28 | G21: =+F21*(1+C11) -> 437805.88 | H21: =+G21*(1+C12) -> 463430.56 | J21: +10% | K21: =K22*1.1 -> 382613
B22: Total Ingresos operacionales | C22: 0 | D22: =+D20*D21 -> 1.1521991e+11 | E22: =+E20*E21 -> 1.2797179e+11 | F22: =+F20*F21 -> 1.7777629e+11 | G22: =+G20*G21 -> 1.9765797e+11 | H22: =+H20*H21 -> 2.1968833e+11 | J22: Precio de venta inicial | K22: 347830
J23: Precio de venta critico | K23: =G11 -> 334311.66
B24: Tabla 3. Inversiones | J24: -10% | K24: =K22*0.9 -> 313047
B25: INVERSIONES
B26: Año | C26: 0 | D26: =+C26+1 -> 1 | E26: =+D26+1 -> 2 | F26: =+E26+1 -> 3 | G26: =+F26+1 -> 4 | H26: =+G26+1 -> 5
B27: Activos fijos depreciables | C27: =+SUM('CALCULO COSTOS E INVERSIONES'!G9:G24) -> 30705000 | D27: =+SUM('CALCULO COSTOS E INVERSIONES'!J9:J23) -> 0 | E27: =+SUM('CALCULO COSTOS E INVERSIONES'!M9:M23) -> 11674218 | F27: =+SUM('CALCULO COSTOS E INVERSIONES'!P9:P23) -> 0 | G27: =+SUM('CALCULO COSTOS E INVERSIONES'!S9:S23) -> 0 | H27: =+SUM('CALCULO COSTOS E INVERSIONES'!V9:V23) -> 2398226.2 | J27: +15% | K27: 0.95
B28: Activos diferidos | C28: =+SUM('CALCULO COSTOS E INVERSIONES'!G25:G29) -> 40000000 | D28: 0 | E28: 0 | F28: 0 | G28: 0 | H28: 0 | J28: +10% | K28: 0.9
B29: Terrenos | C29: 0 | D29: 0 | E29: 0 | F29: 0 | G29: 0 | J29: % inicial | K29: 0.8
B30: Capital de trabajo | C30: =+C43 -> 0 | D30: =+D44 -> 9.4260133e+09 | E30: =+E44 -> 9.682833e+08 | F30: =+F44 -> 1.2199661e+09 | G30: =+G44 -> 1.2082941e+09 | H30: =+H44 -> 1.3332695e+09 | J30: % Critico | K30: 0.73473005
B31: Total inversión | C31: =+SUM(C27:C30) -> 70705000 | D31: =+SUM(D27:D30) -> 9.4260133e+09 | E31: =+SUM(E27:E30) -> 9.7995752e+08 | F31: =+SUM(F27:F30) -> 1.2199661e+09 | G31: =+SUM(G27:G30) -> 1.2082941e+09 | H31: =+SUM(H27:H30) -> 1.3356677e+09 | J31: -10% | K31: 0.7
J32: -15% | K32: 0.65
B33: Capital de trabajo neto por el método contable
B34: Año | C34: 0 | D34: =+C34+1 -> 1 | E34: =+D34+1 -> 2 | F34: =+E34+1 -> 3 | G34: =+F34+1 -> 4 | H34: =+G34+1 -> 5
B35: Dias Efectivo | C35: 90 | D35: =+C35 -> 90 | E35: =+D35 -> 90 | F35: =+E35 -> 90 | G35: =+F35 -> 90 | H35: =+G35 -> 90
B36: Efectivo | C36: =+(C56/360)*C35 -> 0 | D36: =+(D56/360)*D35 -> 1.5229741e+09 | E36: =+(E56/360)*E35 -> 1.6165944e+09 | F36: =+(F56/360)*F35 -> 1.7110448e+09 | G36: =+(G56/360)*G35 -> 1.8118086e+09 | H36: =+(H56/360)*H35 -> 1.9178534e+09
B37: Dias inventario | C37: 30 | D37: =+C37 -> 30 | E37: =+D37 -> 30 | F37: =+E37 -> 30 | G37: =+F37 -> 30 | H37: =+G37 -> 30
B38: Inventario | C38: =+(C55/360)*C37 -> 0 | D38: =+(D55/360)*D37 -> 9.6821169e+09 | E38: =+(E55/360)*E37 -> 1.0753678e+10 | F38: =+(F55/360)*F37 -> 1.1951065e+10 | G38: =+(G55/360)*G37 -> 1.3287617e+10 | H38: =+(H55/360)*H37 -> 1.4768615e+10
B39: Dias CXC | C39: 1.5 | D39: =+C39 -> 1.5 | E39: =+D39 -> 1.5 | F39: =+E39 -> 1.5 | G39: =+F39 -> 1.5 | H39: =+G39 -> 1.5
B40: CXC | C40: =+(C22/360)*C39 -> 0 | D40: =+(D22/360)*D39 -> 4.8008297e+08 | E40: =+(E22/360)*E39 -> 5.3321579e+08 | F40: =+(F22/360)*F39 -> 7.4073456e+08 | G40: =+(G22/360)*G39 -> 8.2357489e+08 | H40: =+(H22/360)*H39 -> 9.1536805e+08
B41: Dias proveedores | C41: 7 | D41: =+C41 -> 7 | E41: =+D41 -> 7 | F41: =+E41 -> 7 | G41: =+F41 -> 7 | H41: =+G41 -> 7
B42: CXP | C42: =+(C55/360)*C41 -> 0 | D42: =+(D55/360)*D41 -> 2.2591606e+09 | E42: =+(E55/360)*E41 -> 2.5091915e+09 | F42: =+(F55/360)*F41 -> 2.7885819e+09 | G42: =+(G55/360)*G41 -> 3.100444e+09 | H42: =+(H55/360)*H41 -> 3.4460102e+09
B43: Capital de trabajo | C43: =+C36+C38+C40-C42 -> 0 | D43: =+D36+D38+D40-D42 -> 9.4260133e+09 | E43: =+E36+E38+E40-E42 -> 1.0394297e+10 | F43: =+F36+F38+F40-F42 -> 1.1614263e+10 | G43: =+G36+G38+G40-G42 -> 1.2822557e+10 | H43: =+H36+H38+H40-H42 -> 1.4155826e+10
B44: Variacion | D44: =+D43-C43 -> 9.4260133e+09 | E44: =+E43-D43 -> 9.682833e+08 | F44: =+F43-E43 -> 1.2199661e+09 | G44: =+G43-F43 -> 1.2082941e+09 | H44: =+H43-G43 -> 1.3332695e+09
B46: Tabla 4. Datos para el cálculo de la depreciación y amortización de activos
B47: Datos para cálculo de depreciación y amortización de activos
B48: Vida útil activos depreciables (años | C48: 5 y 10
B49: Periodo amortización diferidos e intangibles (años) | C49: 5
B51: Tabla 5. Datos apra el cálculo de los egresos
B52: DATOS PARA EL CÁLCULO DE EGRESOS
B53: Año | C53: 0 | D53: 1 | E53: 2 | F53: 3 | G53: 4 | H53: 5
B54: Costo variable unitario ($/kg) | C54: =+'PROYECCIONES Y ESTIMACIONES'!R18 -> 267561.11 | D54: =+C54*(1+C8) -> 284072.31 | E54: =+D54*(1+C9) -> 300487.43 | F54: =+E54*(1+C10) -> 318043.55 | G54: =+F54*(1+C11) -> 336773.22 | H54: =+G54*(1+C12) -> 356484.48
B55: Costos variables totales (millones de pesos) | C55: 0 | D55: =+'CALCULO COSTOS E INVERSIONES'!I49 -> 1.161854e+11 | E55: =+'CALCULO COSTOS E INVERSIONES'!L49 -> 1.2904413e+11 | F55: =+'CALCULO COSTOS E INVERSIONES'!O49 -> 1.4341278e+11 | G55: =+'CALCULO COSTOS E INVERSIONES'!R49 -> 1.5945141e+11 | H55: =+'CALCULO COSTOS E INVERSIONES'!U49 -> 1.7722338e+11
B56: Costos fijos por año | C56: 0 | D56: =+'CALCULO COSTOS E INVERSIONES'!I66 -> 6.0918963e+09 | E56: =+'CALCULO COSTOS E INVERSIONES'!L66 -> 6.4663777e+09 | F56: =+'CALCULO COSTOS E INVERSIONES'!O66 -> 6.8441791e+09 | G56: =+'CALCULO COSTOS E INVERSIONES'!R66 -> 7.2472345e+09 | H56: =+'CALCULO COSTOS E INVERSIONES'!U66 -> 7.6714135e+09
B57: Gastos de administración y ventas | C57: 0 | D57: =+'GASTOS ADMINISTRATIVOS'!H13 -> 3.512907e+08 | E57: =+'GASTOS ADMINISTRATIVOS'!J13 -> 6.6508576e+08 | F57: =+'GASTOS ADMINISTRATIVOS'!L13 -> 7.3760671e+08 | G57: =+'GASTOS ADMINISTRATIVOS'!N13 -> 8.1937779e+08 | H57: =+'GASTOS ADMINISTRATIVOS'!P13 -> 9.0972403e+08
B58: Vlr de rescate (millones de pesos corrientes) | C58: =+G64 -> 5625000
B60: Valor de rescate por el método de calculo contable
C61: Valor Activo | D61: Años de depreciacion | E61: Depreciacion Anual | F61: Años evaluacion | G61: Valor de desecho
B62: Activos fijos depreciables a 5 años | C62: =+('CALCULO COSTOS E INVERSIONES'!G9+'CALCULO COSTOS E INVERSIONES'!G10+'CALCULO COSTOS E INVERSIONES'!G12+'CALCULO COSTOS E INVERSIONES'!G14+'CALCULO COSTOS E INVERSIONES'!G15+'CALCULO COSTOS E INVERSIONES'!G16+'CALCULO COSTOS E INVERSIONES'!G18+'CALCULO COSTOS E INVERSIONES'!G19+'CALCULO COSTOS E INVERSIONES'!G22+'CALCULO COSTOS E INVERSIONES'!G23+'CALCULO COSTOS E INVERSIONES'!G24) -> 19455000 | D62: 5 | E62: =+C62/D62 -> 3891000 | F62: 5 | G62: =+C62-(E62*F62) -> 0
B63: Activos fijos depreciables a 10 años | C63: =+('CALCULO COSTOS E INVERSIONES'!G11+'CALCULO COSTOS E INVERSIONES'!G13+'CALCULO COSTOS E INVERSIONES'!G17+'CALCULO COSTOS E INVERSIONES'!G20+'CALCULO COSTOS E INVERSIONES'!G21) -> 11250000 | D63: 10 | E63: =+C63/D63 -> 1125000 | F63: 5 | G63: =+C63-(E63*F63) -> 5625000
F64: Valor de rescate | G64: =+SUM(G63:G63) -> 5625000
B66: Tabla 6. Datos para el cálculo de la financiación
B67: FINANCIACIÓN
B68: Préstamo (millones) | C68: 50000000
B69: Interés efectivo | C69: 0.2489 | D69: EA
B70: Forma de pago | C70: Cinco cuotas iguales
B71: Número de cuotas | C71: 5
B73: Tabla 7. Tarifa impositiva
B74: IMPUESTOS
B75: Impuesto de renta (%) | C75: 0.35
B77: Tabla 8. Cálculo de los costos de oportunidad
B78: COSTO DE OPORTUNIDAD
B79: Costo de oportunidad en térnimos nominales | C79: 0.15
B80: Porcentaje financiado con recursos propios | C80: =+(C31-C68)/C31 -> 0.29283643
B81: Costo de la deuda d.d.i (k.d.d.i=Kd(1-t)) | C81: =+C69*(1-C75) -> 0.161785
B82: CCP ddi en términos nominales | C82: =+(C80*C79)+(1-C80)*C81 -> 0.15833392
B84: Tabla 9. | F84: Tabla 10
B85: Depreciación | F85: Amortización de Inversiones
B86: Millones de pesos | F86: Millones de pesos
B87: Fin Año | C87: Depreciación anual ( 5 años ) | D87: Depreciación anual ( 10 años ) | F87: Fin Año | G87: Amortización anual pesos corrientes
B88: 1 | C88: =+('CALCULO COSTOS E INVERSIONES'!G9+'CALCULO COSTOS E INVERSIONES'!G10+'CALCULO COSTOS E INVERSIONES'!G12+'CALCULO COSTOS E INVERSIONES'!G14+'CALCULO COSTOS E INVERSIONES'!G15+'CALCULO COSTOS E INVERSIONES'!G16+'CALCULO COSTOS E INVERSIONES'!G18+'CALCULO COSTOS E INVERSIONES'!G19+'CALCULO COSTOS E INVERSIONES'!G22+'CALCULO COSTOS E INVERSIONES'!G23+'CALCULO COSTOS E INVERSIONES'!G24)/5 -> 3891000 | D88: =+('CALCULO COSTOS E INVERSIONES'!G11+'CALCULO COSTOS E INVERSIONES'!G13+'CALCULO COSTOS E INVERSIONES'!G17+'CALCULO COSTOS E INVERSIONES'!G20+'CALCULO COSTOS E INVERSIONES'!G21)/10 -> 1125000 | F88: 1 | G88: =+(C28-25000000)/C49 -> 3000000
B89: 2 | C89: =+C88 -> 3891000 | D89: =+D88 -> 1125000 | F89: 2 | G89: =+G88 -> 3000000
B90: 3 | C90: =+C89 -> 3891000 | D90: =+D89 -> 1125000 | F90: 3 | G90: =+G89 -> 3000000
B91: 4 | C91: =+C90 -> 3891000 | D91: =+D90 -> 1125000 | F91: 4 | G91: =+G90 -> 3000000
B92: 5 | C92: =+C91 -> 3891000 | D92: =+D91 -> 1125000 | F92: 5 | G92: =+G91 -> 3000000
B94: Tabla 11
B95: Flujo de caja proyectado para el calculo de la TIR y VPN del proyecto puro despues de impuestos
B96: 0
B97: Concepto | C97: 0 | D97: 1 | E97: 2 | F97: 3 | G97: 4 | H97: 5
B98: +Ingresos por ventas | C98: 0 | D98: =+D22 -> 1.1521991e+11 | E98: =+E22 -> 1.2797179e+11 | F98: =+F22 -> 1.7777629e+11 | G98: =+G22 -> 1.9765797e+11 | H98: =+H22 -> 2.1968833e+11
B99: - Costo de producción variable | C99: 0 | D99: =+D55 -> 1.161854e+11 | E99: =+E55 -> 1.2904413e+11 | F99: =+F55 -> 1.4341278e+11 | G99: =+G55 -> 1.5945141e+11 | H99: =+H55 -> 1.7722338e+11
B100: - Costo de producción fijo | C100: 0 | D100: =+D56 -> 6.0918963e+09 | E100: =+E56 -> 6.4663777e+09 | F100: =+F56 -> 6.8441791e+09 | G100: =+G56 -> 7.2472345e+09 | H100: =+H56 -> 7.6714135e+09
B101: - Gastos de administración y ventas | C101: 0 | D101: =+D57 -> 3.512907e+08 | E101: =+E57 -> 6.6508576e+08 | F101: =+F57 -> 7.3760671e+08 | G101: =+G57 -> 8.1937779e+08 | H101: =+H57 -> 9.0972403e+08
B102: = Renta bruta | C102: =+C98-(C99+C100+C101) -> 0 | D102: =+D98-(D99+D100+D101) -> -7.4086777e+09 | E102: =+E98-(E99+E100+E101) -> -8.2038092e+09 | F102: =+F98-(F99+F100+F101) -> 2.6781725e+10 | G102: =+G98-(G99+G100+G101) -> 3.0139953e+10 | H102: =+H98-(H99+H100+H101) -> 3.3883813e+10
B103: -Amortización intangibles | C103: 0 | D103: =+G88 -> 3000000 | E103: =+D103 -> 3000000 | F103: =+E103 -> 3000000 | G103: =+F103 -> 3000000 | H103: =+G103 -> 3000000
B104: -Depreciación | C104: 0 | D104: =+C88+D88 -> 5016000 | E104: =+D104 -> 5016000 | F104: =+E104 -> 5016000 | G104: =+F104 -> 5016000 | H104: =+G104 -> 5016000
B105: = Renta Líquida Gravable (RLG) | C105: =+C102-C103-C104 -> 0 | D105: =+D102-D103-D104 -> -7.4166937e+09 | E105: =+E102-E103-E104 -> -8.2118252e+09 | F105: =+F102-F103-F104 -> 2.6773709e+10 | G105: =+G102-G103-G104 -> 3.0131937e+10 | H105: =+H102-H103-H104 -> 3.3875797e+10
B106: -Impuesto de renta | D106: 0 | E106: 0 | F106: =+F105*$C$75 -> 9.3707982e+09 | G106: =+G105*$C$75 -> 1.0546178e+10 | H106: =+H105*$C$75 -> 1.1856529e+10
B107: +Amortización intangibles | D107: =+D103 -> 3000000 | E107: =+E103 -> 3000000 | F107: =+F103 -> 3000000 | G107: =+G103 -> 3000000 | H107: =+H103 -> 3000000
B108: +Depreciación | D108: =+D104 -> 5016000 | E108: =+E104 -> 5016000 | F108: =+F104 -> 5016000 | G108: =+G104 -> 5016000 | H108: =+H104 -> 5016000
B109: -Activos depreciables | C109: =+C27 -> 30705000 | D109: =+D27 -> 0 | E109: =+E27 -> 11674218 | F109: =+F27 -> 0 | G109: =+G27 -> 0 | H109: =+H27 -> 2398226.2
B110: -Activos Diferidos | C110: =+C28 -> 40000000 | D110: =+D28 -> 0 | E110: =+E28 -> 0 | F110: =+F28 -> 0 | G110: =+G28 -> 0 | H110: =+H28 -> 0
B111: -Terrenos | C111: =+C29 -> 0 | D111: 0 | E111: 0 | F111: 0 | G111: 0 | H111: 0
...
